Workbook
Name ClientList: '_FilterLists'!$B$1:$B$48
Name SubCategoryList: '_FilterLists'!$A$1:$A$28

Sheet _FilterLists
A1: All | B1: All
A2: Access control/CCTV/Security System | B2: Algoworks
A3: Animal Movement | B3: Alight Solutions
A4: Carpentry | B4: Alphagrep Securities
A5: Civil | B5: Apcer Life Sciences India Limited
A6: Cleaning | B6: Atkins
A7: Compliance and Policy Violations | B7: BAYSTREET ADVISORS PRIVATE LIMITED
A8: Drinking water | B8: Baker Hughes
A9: Electrical | B9: Bayer
A10: Ergonomic Impacts | B10: Brillio
A11: Food & Beverages | B11: CBRE D&T
A12: HVAC | B12: Centrient Pharma
... A28: Workplace Violence | B28: Nimbuspay Innovations India Private Limited
B29: PWC - Pricewaterhouse Cooper Pvt. Ltd.
B30: PricewaterhouseCoopers Service Delivery Center (Kolkata) Private Limited
B31: Pubmatic
B32: ROHM SEMICONDUCTOR INDIA PRIVATE LIMITED
B33: SSandC
B34: Sainsbury's
B35: Siemens
B36: Table Space
B37: Teleflex
B38: Thermofisher
B39: Topsoe India Private Limited
B40: Tresvista
... B48: Zelestra

Sheet Dashboard
B1: 📊 Client Tracker NCR - Dashboard
B2: Incident Management & Client Overview | Use dropdown filters below to analyze data
B4: 🏙 City | C4: 🏢 Facility | D4: 📅 Month | E4: 📂 Category | F4: 🔧 Sub-Category | G4: 🚦 Status | H4: 👥 Client | I4: ⚠️ Business Impact | J4: ⏳ Bucket | K4: 📅 From Date | L4: 📅 To Date
B5: All | C5: All | D5: All | E5: All | F5: All | G5: All | H5: All | I5: All | J5: All
B6: ⬆️ Use the dropdown filters above to filter data. Select "All" to show everything. Enter dates in From/To Date cells for date range filtering. Charts and formulas update when you open the file in Excel.
B8: TOTAL INCIDENTS | D8: OPEN | F8: CLOSED | H8: IN PROGRESS | J8: BUSINESS IMPACT | L8: UNIQUE SITES
B9: ='Dashboard Formula (Reference)'!B2 -> 355 | D9: ='Dashboard Formula (Reference)'!B3 -> 5 | F9: ='Dashboard Formula (Reference)'!B4 -> 348 | H9: ='Dashboard Formula (Reference)'!B5 -> 2 | J9: ='Dashboard Formula (Reference)'!B6 -> 99 | L9: ='Dashboard Formula (Reference)'!B7 -> 11

Sheet Dashboard Formula (Reference)
A1: KPI Metric | B1: Count | D1: Category | E1: Count | G1: Month | H1: Count | J1: Status | K1: Count | M1: City | N1: Count
A2: Total Incidents | B2: =COUNTA(Incidents!H2:H356) -> 355 | D2: Engineering & Building Services | E2: =COUNTIF(Incidents!L2:L356,D2) -> 218 | G2: Nov'24 | H2: =COUNTIF(Incidents!D2:D356,G2) -> 17 | J2: Open | K2: =COUNTIF(Incidents!R2:R356,J2) -> 5 | M2: Gurugram | N2: =COUNTIF(Incidents!A2:A356,M2) -> 237
A3: Open | B3: =COUNTIF(Incidents!R2:R356,"Open") -> 5 | D3: Security | E3: =COUNTIF(Incidents!L2:L356,D3) -> 61 | G3: Dec'24 | H3: =COUNTIF(Incidents!D2:D356,G3) -> 24 | J3: In Progress | K3: =COUNTIF(Incidents!R2:R356,J3) -> 2 | M3: Noida | N3: =COUNTIF(Incidents!A2:A356,M3) -> 118
A4: Closed | B4: =COUNTIF(Incidents!R2:R356,"Closed") -> 348 | D4: Operations | E4: =COUNTIF(Incidents!L2:L356,D4) -> 28 | G4: Jan'25 | H4: =COUNTIF(Incidents!D2:D356,G4) -> 26 | J4: Closed | K4: =COUNTIF(Incidents!R2:R356,J4) -> 348
A5: In Progress | B5: =COUNTIF(Incidents!R2:R356,"In Progress") -> 2 | D5: Health & Safety | E5: =COUNTIF(Incidents!L2:L356,D5) -> 25 | G5: Feb'25 | H5: =COUNTIF(Incidents!D2:D356,G5) -> 24
A6: Business Impact (Yes) | B6: =COUNTIF(Incidents!O2:O356,"Yes") -> 99 | D6: Others | E6: =COUNTIF(Incidents!L2:L356,D6) -> 21 | G6: Mar'25 | H6: =COUNTIF(Incidents!D2:D356,G6) -> 16
A7: Unique Sites | B7: =SUMPRODUCT(1/COUNTIF(Incidents!B2:B356,Incidents!B2:B356)) -> 11 | D7: Traffic & Transport | E7: =COUNTIF(Incidents!L2:L356,D7) -> 2 | G7: Apr'25 | H7: =COUNTIF(Incidents!D2:D356,G7) -> 19
G8: May'25 | H8: =COUNTIF(Incidents!D2:D356,G8) -> 13
G9: Jun'25 | H9: =COUNTIF(Incidents!D2:D356,G9) -> 12
A10: Business Impact | B10: Count | D10: Aging Bucket | E10: Count | G10: Facility | H10: Count | J10: Sub-Category | K10: Count
A11: Yes | B11: =COUNTIF(Incidents!O2:O356,A11) -> 99 | D11: 0 - 5 Days | E11: =COUNTIF(Incidents!F2:F356,D11) -> 2 | G11: DLF 10 B&C | H11: =COUNTIF(Incidents!B2:B356,G11) -> 120 | J11: Electrical | K11: =COUNTIF(Incidents!M2:M356,J11) -> 62
A12: No | B12: =COUNTIF(Incidents!O2:O356,A12) -> 256 | D12: 5 - 10 Days | E12: =COUNTIF(Incidents!F2:F356,D12) -> 3 | G12: Capital City BPTP | H12: =COUNTIF(Incidents!B2:B356,G12) -> 89 | J12: Safety security systems | K12: =COUNTIF(Incidents!M2:M356,J12) -> 49
D13: 10 - 20 Days | E13: =COUNTIF(Incidents!F2:F356,D13) -> 9 | G13: Cyber Green | H13: =COUNTIF(Incidents!B2:B356,G13) -> 53 | J13: Plumbing | K13: =COUNTIF(Incidents!M2:M356,J13) -> 39
D14: 20 - 30 Days | E14: =COUNTIF(Incidents!F2:F356,D14) -> 9 | G14: DLF Tech Park | H14: =COUNTIF(Incidents!B2:B356,G14) -> 29 | J14: Access control/CCTV/Security System | K14: =COUNTIF(Incidents!M2:M356,J14) -> 23
D15: 30 + Days | E15: =COUNTIF(Incidents!F2:F356,D15) -> 332 | G15: DLF Downtown - Gurgaon | H15: =COUNTIF(Incidents!B2:B356,G15) -> 21 | J15: Medical Emergencies | K15: =COUNTIF(Incidents!M2:M356,J15) -> 18
G16: Two Horizon | H16: =COUNTIF(Incidents!B2:B356,G16) -> 17 | J16: Others | K16: =COUNTIF(Incidents!M2:M356,J16) -> 17
G17: DLF 8 | H17: =COUNTIF(Incidents!B2:B356,G17) -> 14 | J17: Compliance and Policy Violations | K17: =COUNTIF(Incidents!M2:M356,J17) -> 16
G18: DLF 6 | H18: =COUNTIF(Incidents!B2:B356,G18) -> 7 | J18: HVAC | K18: =COUNTIF(Incidents!M2:M356,J18) -> 16
G19: Good Earth Business Bay II | H19: =COUNTIF(Incidents!B2:B356,G19) -> 2 | J19: Carpentry | K19: =COUNTIF(Incidents!M2:M356,J19) -> 14
G20: Global Gateway | H20: =COUNTIF(Incidents!B2:B356,G20) -> 2 | J20: Others (Engineering) | K20: =COUNTIF(Incidents!M2:M356,J20) -> 13
G21: DLF 5 A | H21: =COUNTIF(Incidents!B2:B356,G21) -> 1 | J21: Food & Beverages | K21: =COUNTIF(Incidents!M2:M356,J21) -> 11
J22: Civil | K22: =COUNTIF(Incidents!M2:M356,J22) -> 11
J23: Security System Incidents | K23: =COUNTIF(Incidents!M2:M356,J23) -> 7
J24: Drinking water | K24: =COUNTIF(Incidents!M2:M356,J24) -> 6
J25: Theft or Loss | K25: =COUNTIF(Incidents!M2:M356,J25) -> 6
J26: Pest Control | K26: =COUNTIF(Incidents!M2:M356,J26) -> 5
J27: Unauthorized Access | K27: =COUNTIF(Incidents!M2:M356,J27) -> 5
J28: Workplace Violence | K28: =COUNTIF(Incidents!M2:M356,J28) -> 4
J29: Harm to People | K29: =COUNTIF(Incidents!M2:M356,J29) -> 3
J30: Animal Movement | K30: =COUNTIF(Incidents!M2:M356,J30) -> 2
J31: Housekeeping | K31: =COUNTIF(Incidents!M2:M356,J31) -> 2
J32: Natural Disasters | K32: =COUNTIF(Incidents!M2:M356,J32) -> 2
J33: Other | K33: =COUNTIF(Incidents!M2:M356,J33) -> 1
J34: Restroom Cleaning | K34: =COUNTIF(Incidents!M2:M356,J34) -> 1
J35: Cleaning | K35: =COUNTIF(Incidents!M2:M356,J35) -> 1
J36: Vehicle Damage | K36: =COUNTIF(Incidents!M2:M356,J36) -> 1
J37: Ergonomic Impacts | K37: =COUNTIF(Incidents!M2:M356,J37) -> 1

Sheet Client MOM
A1: Location | B1: Site Name | C1: Client Name | D1: Client Category | E1: TS Suites / TS Managed | F1: Floor Details | G1: On-going Issues | H1: Appreciation | I1: Sales Expansion
A2: Noida | B2: Capital City BPTP | C2: Clearwater Analytics | D2: Diamond | E2: TS Managed | F2: 10 | G2: 1. Lux level need to be increased on workstation area.
A3: Noida | B3: Capital City BPTP | C3: Clearwater Analytics | D3: Diamond | E3: TS Managed | F3: 10 | G3: 2. Faulty Lock to be replace.
A4: Noida | B4: Capital City BPTP | C4: Clearwater Analytics | D4: Diamond | E4: TS Managed | F4: 10 | G4: 3. Paint to be done at highlighted areas.
A5: Noida | B5: Capital City BPTP | C5: DSV | E5: TS Managed | F5: BPTP Capital City 11th Floor | G5: 1. Gypsum cracks need to be re-filled & paint touch required in entire office area.
A6: Noida | B6: Capital City BPTP | C6: Dedalus | E6: TS Managed | F6: BPTP Capital City 12th Floor | G6: 1. Main Door frame need to be replace with new one.
A7: Noida | B7: Capital City BPTP | C7: Dedalus | E7: TS Managed | F7: BPTP Capital City 12th Floor | G7: 2. Internet issue to be resolved.
A8: Noida | B8: Capital City BPTP | C8: IBM | E8: TS Managed | F8: BPTP Capital City 12th Floor
A9: Noida | B9: Capital City BPTP | C9: Siemens | E9: TS Managed | F9: BPTP Capital City 12th Floor | G9: 1. Invoices pertaining to chargeback to be share on timely basis.
A10: Noida | B10: Capital City BPTP | C10: Siemens | E10: TS Managed | F10: BPTP Capital City 12th Floor | G10: 2. Housekeeping services to be improved.
A11: Noida | B11: Capital City BPTP | C11: Siemens | E11: TS Managed | F11: BPTP Capital City 12th Floor | G11: 3. Pantry floor mat to be replace.
A12: Noida | B12: Capital City BPTP | C12: Thermofisher | E12: TS Suites | F12: BPTP Capital City 13th Floor | G12: 1. Cleaning to be maintain on a regular basis.
A13: Noida | B13: Capital City BPTP | C13: Voya | E13: TS Suites | F13: BPTP Capital City 13th Floor | G13: 1. Coffee machine Breakdown.
A14: Noida | B14: Capital City BPTP | C14: Voya | E14: TS Suites | F14: BPTP Capital City 13th Floor | G14: 2. Pantry staff to be available in late night hours.
A15: Noida | B15: Capital City BPTP | C15: Atkins | E15: TS Suites | F15: BPTP Capital City 15th Floor | G15: 1. Internet services to be improve.
A16: Noida | B16: Capital City BPTP | C16: CBRE D&T | E16: TS Managed / TS Suites | F16: BPTP Capital City 15th Floor
A17: Noida | B17: Capital City BPTP | C17: Dayforce | E17: TS Managed | F17: BPTP Capital City 15th Floor | G17: 1. Drinking water RO to be maintained under AMC.
A18: Noida | B18: Capital City BPTP | C18: Dayforce | E18: TS Managed | F18: BPTP Capital City 15th Floor | G18: 2. Housekeeping service to be maintained.
A19: Noida | B19: Capital City BPTP | C19: Nimbuspay Innovations | E19: TS Managed | F19: BPTP Capital City 15th Floor | H19: "Hi Lipin, Rohit, I hope you’re doing well. I would like to take a moment to sincerely thank Pushpendra and his team for their exceptional support and service. I would especially like to acknowledge Pushpendra for his kind, considerate, and attentive approach. He is extremely proactive and always a call away, played a significant role in ensuring the smooth management of our client visit. Thank you once again for your dedication and outstanding support. 😊 With Regards Isha Saxena Sr. VP- Human Resource 8800940017 Nimbuspay Technologies Inc. "
A20: Noida | B20: Capital City BPTP | C20: Switchfly | E20: TS Suites | F20: BPTP Capital City 15th Floor | G20: 1. GST Plate & Frosting work to be completed on chargeback cost.
A21: Noida | B21: Capital City BPTP | C21: Teleflex | E21: TS Suites | F21: BPTP Capital City 15th Floor | G21: 1. Pantry operations to be monitored.
A22: Noida | B22: Capital City BPTP | C22: Apcer | E22: TS Managed | F22: BPTP Capital City 9th Floor
A23: Noida | B23: Capital City BPTP | C23: Naviga | E23: TS Managed | F23: BPTP Capital City 9th Floor | G23: 1 Pantries to be set properly every morning.
A24: Noida | B24: Capital City BPTP | C24: Rohm Semiconductor India Private Limited | E24: TS Managed | F24: BPTP Capital City 9th Floor
A25: Gurugram | B25: DLF 6 | C25: ETS | E25: TS Managed | F25: DLF 6, 4th floor | G25: Project Related Issues 1. Negative Air pressure due to which doors are not closing properly
A26: Gurugram | B26: DLF 10 B&C | C26: Baker Hughes | E26: TS Managed | F26: DLF Cyber City 10B&C, 10th floor
A27: Gurugram | B27: DLF 10 B&C | C27: Berkadia | E27: TS Managed | F27: DLF Cyber City 10B&C, 10th floor | G27: Housekeeping issues due to staff scarcity during B-Shift
A28: Gurugram | B28: DLF 10 B&C | C28: Centrient Pharma | E28: TS Managed | F28: DLF Cyber City 10B&C, 10th floor | G28: 1. Pest Control
A29: Gurugram | B29: DLF 10 B&C | C29: Centrient Pharma | E29: TS Managed | F29: DLF Cyber City 10B&C, 10th floor | G29: 2. Housekeeping
A30: Gurugram | B30: DLF 10 B&C | C30: Centrient Pharma | E30: TS Managed | F30: DLF Cyber City 10B&C, 10th floor | G30: 3. Pantry Services
A31: Gurugram | B31: DLF 10 B&C | C31: Centrient Pharma | E31: TS Managed | F31: DLF Cyber City 10B&C, 10th floor | G31: 4. Coffee Machine Breakdown
A32: Gurugram | B32: DLF 10 B&C | C32: Centrient Pharma | E32: TS Managed | F32: DLF Cyber City 10B&C, 10th floor | G32: 5. Housekeeping issues due to staff scarcity during B-Shift
A33: Gurugram | B33: DLF 10 B&C | C33: NTT India Private Limited | E33: TS Managed | F33: DLF Cyber City 10B&C, 10th floor | G33: 1. WC Blocakge Issue
A34: Gurugram | B34: DLF 10 B&C | C34: NTT India Private Limited | E34: TS Managed | F34: DLF Cyber City 10B&C, 10th floor | G34: 2. Linear Light Faulty
A35: Gurugram | B35: DLF 10 B&C | C35: NTT India Private Limited | E35: TS Managed | F35: DLF Cyber City 10B&C, 10th floor | G35: 3. Pantry Cupboard need to be fixed
A36: Gurugram | B36: DLF 10 B&C | C36: NTT India Private Limited | E36: TS Managed | F36: DLF Cyber City 10B&C, 10th floor | G36: 4. Housekeeping issues due to staff scarcity during B-Shift
A37: Gurugram | B37: DLF 10 B&C | C37: Pubmatic | E37: TS Managed | F37: DLF Cyber City 10B&C, 10th floor | G37: 1. Coffee Machine Breakdown
A38: Gurugram | B38: DLF 10 B&C | C38: Pubmatic | E38: TS Managed | F38: DLF Cyber City 10B&C, 10th floor | G38: 2. CCTV Footage access on their domain
... A45: Gurugram | B45: DLF 10 B&C | C45: Vialto | E45: TS Managed | F45: DLF Cyber City 10B&C, 2nd floor | G45: 3. Unauthorized parking Issue
A46: Gurugram | B46: DLF 10 B&C | C46: Graviton | E46: TS Managed | F46: DLF Cyber City 10B&C, 3rd floor
A47: Gurugram | B47: DLF 10 B&C | C47: Resolven | E47: TS Managed | F47: DLF Cyber City 10B&C, 3rd floor | G47: Printer restoration (Konika Minolta) | I47: Due to Management change they are looking out for their own space
A48: Gurugram | B48: DLF 10 B&C | C48: Hitachi Systems | E48: TS Managed | F48: DLF Cyber City 10B&C, 10th floor | G48: 1. Wall Paint Required
A49: Gurugram | B49: DLF 10 B&C | C49: Hitachi Systems | E49: TS Managed | F49: DLF Cyber City 10B&C, 10th floor | G49: 2.Ceiling tile replacement
A50: Gurugram | B50: DLF 10 B&C | C50: Hitachi Systems | E50: TS Managed | F50: DLF Cyber City 10B&C, 10th floor | G50: 3. Carpet shompooing / replacement for entire floor
A51: Gurugram | B51: DLF 10 B&C | C51: Hitachi Systems | E51: TS Managed | F51: DLF Cyber City 10B&C, 4th floor | G51: 1. Carpet shompooing / replacement for entire floor
A52: Gurugram | B52: DLF 10 B&C | C52: Hitachi Systems | E52: TS Managed | F52: DLF Cyber City 10B&C, 4th floor | G52: 2. Workstation partion replacement
A53: Gurugram | B53: DLF 10 B&C | C53: Hitachi Systems | E53: TS Managed | F53: DLF Cyber City 10B&C, 4th floor | G53: 3. Wallpaper replacement
A54: Gurugram | B54: DLF 10 B&C | C54: Hitachi Systems | E54: TS Managed | F54: DLF Cyber City 10B&C, 4th floor | G54: 4. Acustic replacement in cabin, meeting, board-room
A55: Gurugram | B55: DLF 10 B&C | C55: Hitachi Systems | E55: TS Managed | F55: DLF Cyber City 10B&C, 4th floor | G55: 5. Water seepage on wall due to AHU 6. Housekeeping issues due to staff scarcity during B-Shift
A56: Gurugram | B56: DLF 10 B&C | C56: Hitachi Systems | E56: TS Managed | F56: DLF Cyber City 10B&C, 4th floor | G56: 6. Housekeeping issues due to staff scarcity during B-Shift
A57: Gurugram | B57: DLF 10 B&C | C57: SSandC | E57: TS Managed | F57: DLF Cyber City 10B&C, 5th floor
A58: Gurugram | B58: DLF 10 B&C | C58: Circle K | E58: TS Managed | F58: DLF Cyber City 10B&C, 9th floor | G58: 1. Pest Control | I58: Client has asked for additonal Space
A59: Gurugram | B59: DLF 10 B&C | C59: Circle K | E59: TS Managed | F59: DLF Cyber City 10B&C, 9th floor | G59: 2. Lobby Lisiting
A60: Gurugram | B60: DLF 10 B&C | C60: Circle K | E60: TS Managed | F60: DLF Cyber City 10B&C, 9th floor | G60: 3. Housekeeping issues due to staff scarcity during B-Shift
A61: Gurugram | B61: DLF 10 B&C | C61: Unifocus | E61: TS Managed | F61: DLF Cyber City 10B&C, 9th floor
A62: Gurugram | B62: DLF 8 | C62: Houlihan Lokey | D62: Diamond | E62: TS Managed | F62: DLF Cyber City 8B, 7th Floor | G62: HAT Workstation Hydrolic Issue
A63: Gurugram | B63: DLF 8 | C63: IAC | E63: TS Managed | F63: DLF Cyber City 8B, 7th Floor
A64: Gurugram | B64: DLF 8 | C64: Leapwork | E64: TS Managed | F64: DLF Cyber City 8B, 7th Floor | G64: Client Branding on TS Reception
A65: Gurugram | B65: DLF 8 | C65: Midrex | E65: TS Managed | F65: DLF Cyber City 8B, 7th Floor
A66: Gurugram | B66: DLF 8 | C66: MY Com | E66: TS Managed | F66: DLF Cyber City 8B, 7th Floor
A67: Gurugram | B67: Cyber Green | C67: Alight | E67: TS Managed | F67: DLF Cyber Greens 10th Floor
A68: Gurugram | B68: Cyber Green | C68: Wood Mackenzie | E68: TS Managed | F68: DLF Cyber Greens 8th Floor
A69: Gurugram | B69: Cyber Green | C69: Bayer | E69: TS Managed | F69: DLF Cyber Greens 9th Floor
A70: Gurugram | B70: DLF Downtown - Gurgaon | C70: Mishcon | E70: TS Managed | F70: DLF Down Town, 16th floor
A71: Gurugram | B71: DLF Downtown - Gurgaon | C71: Sainsbury | E71: TS Managed | F71: DLF Down Town, 16th floor
A72: Noida | B72: DLF Tech Park | C72: Algoworks | D72: Managed | F72: DLF Tech Park 6th Floor | H72: Hi Pankaj & Table space team, I fully echo Gunjan’s thoughts. Your team has been extremely supportive throughout our Board Member/CEO visit. As I often say, when a vendor–customer relationship goes beyond the contract, it evolves into a true collaboration and a long-term partnership Regards Lakki CFO
A73: Noida | B73: DLF Tech Park | C73: DAMAC | D73: Managed | F73: DLF Tech Park 5th Floor | G73: 1. Mobile network to be improve in entire office area. | H73: "Thanks Pankaj for giving us your full support during HOLI Celebration .Appreciate !! Regards, Rajeev Chaturvedi Vice President Capability Centre DAMAC SHARED SERVICES INDIA LLP India Mumbai| Noida| Pune E: Rajeev.chaturvedi@damacsharedservices.com "
A74: Noida | B74: DLF Tech Park | C74: Topsoe | D74: Managed | F74: DLF Tech Park 5th Floor | G74: 1.Couple of workstation will be installed in the IT room, and the cost will be borne by TS.\
A75: Noida | B75: DLF Tech Park | C75: Topsoe | D75: Managed | F75: DLF Tech Park 5th Floor | G75: 2.The previously shared quotation will be revised for the frosting work, which will be executed on a chargeback basis.
A76: Noida | B76: DLF Tech Park | C76: Topsoe | D76: Managed | F76: DLF Tech Park 5th Floor | G76: 3. HRT paper rolls will be provided in place of M-Fold paper towels, and the cost will be borne by TS.
A77: Gurugram | B77: Global Gateway | C77: AP Partners | E77: TS Managed | F77: Global Gateway 5th Floor
A78: Gurugram | B78: Global Gateway | C78: Colgate | E78: TS Managed | F78: Global Gateway 5th Floor
A79: Gurugram | B79: Global Gateway | C79: DS Smith | E79: TS Managed | F79: Global Gateway 5th Floor
A80: Gurugram | B80: Global Gateway | C80: Dun & Bradstreet | E80: TS Managed | F80: Global Gateway 5th Floor
A81: Gurugram | B81: Global Gateway | C81: TKWW | E81: TS Managed | F81: Global Gateway 5th Floor
A82: Gurugram | B82: Good Earth Business Bay - II | C82: HEX Advisory | E82: TS Suites | F82: Good Earth Business Bay - II, 3rd Floor
A83: Gurugram | B83: Good Earth Business Bay - II | C83: Baystreet Advisors Private Limited | E83: TS Suites | F83: Good Earth Business Bay - II,3rd Floor
A84: Gurugram | B84: Good Earth Business Bay - II | C84: Terraegis Clean Tech | E84: TS Suites | F84: Good Earth Business Bay - II,3rd Floor
A85: Noida | B85: Capital City BPTP | C85: ZS Associates | D85: Diamond, Multi-city | E85: TS Managed / TS Suites | F85: BPTP | G85: 1.The floor tiles in the recreational area will be replaced to maintain safety and aesthetics.
A86: Noida | B86: Capital City BPTP | C86: ZS Associates | D86: Diamond, Multi-city | E86: TS Managed / TS Suites | F86: BPTP | G86: 2.Access cards will be activated for ZS associates visiting from different cities to ensure smooth entry and movement within the facility.
A87: Noida | B87: Capital City BPTP | C87: ZS Associates | D87: Diamond, Multi-city | E87: TS Managed / TS Suites | F87: BPTP | G87: 3. Anti-skid tape will be installed in the staircase area to enhance safety and prevent slips or accidents.
A88: Noida | B88: Capital City BPTP | C88: ZS Associates | D88: Diamond, Multi-city | E88: TS Managed / TS Suites | F88: BPTP | G88: 4.The floor plan will be replaced and updated as per the revised layout.
A89: Noida | B89: Capital City BPTP | C89: Trintech | D89: Multi-City | E89: TS Suites | F89: BPTP | G89: 1. Suitable temperature to be maintain across office area.
A90: Gurugram | B90: Two Horizon | C90: Alphagrep Securities | E90: TS Managed | F90: Two Horizon 10th Floor | G90: 1. Invoicing Issue - Parking charged for 3 years in one Invoice
A91: Gurugram | B91: Two Horizon | C91: Elan | E91: TS Suites | F91: Two Horizon 10th Floor | G91: 1. Water smell issue
A92: Gurugram | B92: Two Horizon | C92: Elan | E92: TS Suites | F92: Two Horizon 10th Floor | G92: 2. Uneven Flooring
A93: Gurugram | B93: Two Horizon | C93: Truecaller | E93: TS Suites | F93: Two Horizon 10th Floor | G93: 1. Uneven Flooring
A94: Gurugram | B94: Two Horizon | C94: Truecaller | E94: TS Suites | F94: Two Horizon 10th Floor | G94: 2. Internet Issue - Bad Connectivity
A95: Gurugram | B95: Cyber Green | C95: Brillio | D95: Diamond, Multi-city | E95: TS Suites
A96: Gurugram | B96: Cyber Green | C96: PWC | D96: Multi-City | E96: TS Suites

Sheet Incidents
A1: City | B1: Facility | C1: Date | D1: Month | E1: Pending since | F1: Bucket | G1: Closure Status | H1: ID | I1: Request # | J1: Client | K1: Location | L1: Category | M1: Sub-Category | N1: Time Of Occurrence | O1: Business Impact | P1: Description Of Incident | Q1: Corrective Action | R1: Status | S1: Created By | T1: Created At | U1: Updated By | V1: Updated At
A2: Gurugram | B2: DLF Downtown - Gurgaon | C2: 09-Mar-26 | D2: Mar'26 | E2: 2 | F2: 0 - 5 Days | G2: 0 | H2: 2412 | I2: INC_DT16_TBS_2412 | J2: Table Space | K2: DLF Downtown - Block 4, Gurugram, 16th Floor | L2: Engineering & Building Services | M2: Electrical | N2: 46090.438 | O2: No | P2: What: The server room drain pump stopped working automatically. Due to this, water leakage started from the AC unit and the WLD alarm was activated. REQUESTER - Priyanka Malhotra | Q2: 1. Checked and cleaned the drain tray to remove any dirt, debris, or blockage that was preventing the smooth flow of condensate water. 2.Inspected the drain pump float switch and ensured it was free from obstruction. The float mechanism was reset to enable proper automatic operation. 3.Tested the pump operation in manual and auto modes to confirm functionality and ensure the pump restarts automatically when the water level rises.4.Verified electrical connections and control wiring to eliminate any loose contacts or relay issues.5.Conducted a run test to confirm that condensate water is being pumped out efficiently, with no further accumulation or leakage.6 Monitored the AC unit and WLD panel after restoration to ensure stability and normal operating conditions. - Close | R2: Closed | S2: Ravi | T2: 46090.512 | U2: Ravi | V2: 46090.512
A3: Gurugram | B3: Cyber Green | C3: 09-Mar-26 | D3: Mar'26 | E3: 2 | F3: 0 - 5 Days | G3: 1 | H3: 2407 | I3: INC_DLFCG8_TBS_2407 | J3: Wood Mackenzie | K3: DLF Cyber Greens - Tower D & E, 8th Floor | L3: Engineering & Building Services | M3: Electrical | N3: 46090.375 | O3: No | P3: What: - Cafeteria CSU unit balt broken issue. REQUESTER - Sanjay Kumar | R3: Open | S3: Ravi | T3: 46090.401 | U3: Ravi | V3: 46090.401
A4: Noida | B4: Capital City BPTP | C4: 05-Mar-26 | D4: Mar'26 | E4: 6 | F4: 5 - 10 Days | G4: 1 | H4: 2391 | I4: INC_BPTPCC_TBS_2391 | J4: ZS Associates | K4: BPTP Capital City | L4: Engineering & Building Services | M4: Safety security systems | N4: 46086.618 | O4: No | P4: What: A6 alarm is displayed on the thermostat of the server room unit. How: The alarm was triggered due to a communication error between the indoor and outdoor units. REQUESTER - Vishwajeet Kumar | Q4: The vendor has been aligned to check the issue with the indoor unit. The vendor visited the site and observed that an A6 alarm is being displayed on the thermostat due to a faulty PCB card. The PCB card has been sent for repair by the AMC vendor partner. They have confirmed that the faulty card will be replaced by maximum tomorrow. - Inprogress | R4: In Progress | S4: Ravi | T4: 46086.66 | U4: Ravi | V4: 46086.66
A5: Noida | B5: Capital City BPTP | C5: 03-Mar-26 | D5: Mar'26 | E5: 8 | F5: 5 - 10 Days | G5: 0 | H5: 2383 | I5: INC_BPTPCC_TBS_2383 | J5: Naviga | K5: BPTP Capital City | L5: Engineering & Building Services | M5: Electrical | N5: 46084.931 | O5: No | P5: What: 100kVA UPS module fan failure. How: Root Cause Analysis (RCA) is awaited from the vendor. REQUESTER - Vishwajeet Kumar Singh | Q5: We have highlighted the issue to the OEM Team to fixed the issue permanently also same has been brief for Implement during preventive maintenance, including cleaning of UPS internal components and periodic inspection of cooling fans. - Close | R5: Closed | S5: Ravi | T5: 46086.412 | U5: Ravi | V5: 46086.412
A6: Gurugram | B6: Cyber Green | C6: 02-Mar-26 | D6: Mar'26 | E6: 9 | F6: 5 - 10 Days | G6: 0 | H6: 2370 | I6: INC_DLFCG_TBS_2370 | J6: PWC - Pricewaterhouse Cooper Pvt. Ltd. | K6: DLF Cyber Greens - Tower D & E | L6: Engineering & Building Services | M6: Plumbing | N6: 46083.569 | O6: No | P6: What: Water leakage from the sprinkler line. How: Sprinkler joint leakage. REQUESTER - Sonu kumar giri | Q6: We inspected the leakage point and have aligned the project team to resolve the issue. - Close | R6: Closed | S6: Ravi | T6: 46083.653 | U6: Ravi | V6: 46083.653
A7: Noida | B7: DLF Tech Park | C7: 01-Mar-26 | D7: Mar'26 | E7: 10 | F7: 10 - 20 Days | G7: 0 | H7: 2366 | I7: INC_DLFTP5_TBS_2366 | J7: Topsoe India Private Limited | K7: DLF Tech Park, 5th Floor | L7: Engineering & Building Services | M7: Plumbing | N7: 46082.729 | O7: No | P7: What: During a routine inspection, water leakage was noticed from the ceiling on the 5th floor. How: Initial checking shows that the leakage is coming from the 6th floor washroom area, possibly due to a waterproofing problem. REQUESTER - Anoop Singh | Q7: The project team conducted a detailed inspection of the 6th-floor washroom to identify the cause of the leakage, including checking the plumbing lines, floor trap sealing, and waterproofing. The necessary repairs were carried out, damaged parts were replaced, and re-grouting and waterproofing were completed where required. The area has now been properly sealed to prevent further leakage. - Close | R7: Closed | S7: Ravi | T7: 46083.394 | U7: Ravi | V7: 46083.394
A8: Gurugram | B8: DLF Downtown - Gurgaon | C8: 27-Feb-26 | D8: Feb'26 | E8: 12 | F8: 10 - 20 Days | G8: 0 | H8: 2356 | I8: INC_DT16_TBS_2356 | J8: Table Space | K8: DLF Downtown - Block 4, Gurugram, 16th Floor | L8: Security | M8: Workplace Violence | N8: 46080.41 | O8: No | P8: Construction work was in progress at the DT-4 site, and multiple labourers were working in the area. A fight broke out among the labourers. During the incident, a member of the Innovation team named Praveen was assaulted by several labourers. Requester: Priyanka Malhotra | Q8: I immediately sent the security supervisor to the back site area and stopped the fight. Praveen was safely brought to the common area reception, and the site team was informed immediately - Close | R8: Closed | S8: Sree Prabhu | T8: 46080.529 | U8: Sree Prabhu | V8: 46080.529
A9: Gurugram | B9: DLF 10 B&C | C9: 25-Feb-26 | D9: Feb'26 | E9: 14 | F9: 10 - 20 Days | G9: 0 | H9: 2348 | I9: INC_DLF10BF9_TBS_2348 | J9: Circle K | K9: DLF Cyber City 10B&C, 9th floor | L9: Engineering & Building Services | M9: Plumbing | N9: 46078.854 | O9: No | P9: water was found overflowing in the Gents' washroom and Handicapped washroom on the 9th floor. The overflow caused water accumulation on the washroom floor. Requester: Jatin Negi | Q9: The technical team has been informed to check and resolve the issue. The housekeeping team was aligned immediately to clean the affected area and prevent any slip hazards. - Close | R9: Closed | S9: Sree Prabhu | T9: 46079.4 | U9: Sree Prabhu | V9: 46079.4
A10: Noida | B10: DLF Tech Park | C10: 25-Feb-26 | D10: Feb'26 | E10: 14 | F10: 10 - 20 Days | G10: 0 | H10: 2345 | I10: INC_DLFTP6_TBS_2345 | J10: Algoworks | K10: DLF Tech Park, 6th Floor | L10: Engineering & Building Services | M10: Safety security systems | N10: 46078.771 | O10: No | P10: False alarm activated Where: TS common area How: Due to smoke detector malfunctioning Requester: Anoop Sing | Q10: Alarm acknowledges by inhouse team • Team checked and silenced the FAS panel • Visited the location of activation cleaned the smoke detector, and reset the FAS panel • Informed the internal management about the incident • Announcement has been done as per standard speech - Close | R10: Closed | S10: Sree Prabhu | T10: 46079.392 | U10: Sree Prabhu | V10: 46079.392
A11: Gurugram | B11: DLF 10 B&C | C11: 25-Feb-26 | D11: Feb'26 | E11: 14 | F11: 10 - 20 Days | G11: 0 | H11: 2341 | I11: INC_DLFBCC10_TBS_2341 | J11: Table Space | K11: DLF Cyber City - Building No. 10 - Tower B & C, 10th Floor | L11: Engineering & Building Services | M11: Electrical | N11: 46078.542 | O11: No | P11: What: 150 kVA UPS module fan failure. REQUESTER - Sonu Kumar Giri | Q11: We have raised a service ticket and are awaiting the OEM's fan replacement. - Close | R11: Closed | S11: Ravi | T11: 46078.592 | U11: Ravi | V11: 46078.592
A12: Gurugram | B12: Cyber Green | C12: 25-Feb-26 | D12: Feb'26 | E12: 14 | F12: 10 - 20 Days | G12: 0 | H12: 2340 | I12: INC_TBS_2340 | J12: PricewaterhouseCoopers Service Delivery Center (Kolkata) Private Limited | K12: DLF Cyber Greens - Tower D & E, 2nd Floor | L12: Engineering & Building Services | M12: Plumbing | N12: 46078.479 | O12: No | P12: What: Water leakage from ceiling in gent's washroom. How: 3rd floor tower d washroom drain line is blocked. REQUESTER - Yastika Sikka | Q12: The plumber has cleared the drain lines for 3rd floor and water leakage has been resolved for 2nd floor. - Close | R12: Closed | S12: Ravi | T12: 46078.529 | U12: Ravi | V12: 46078.529
A13: Gurugram | B13: Cyber Green | C13: 25-Feb-26 | D13: Feb'26 | E13: 14 | F13: 10 - 20 Days | G13: 0 | H13: 2336 | I13: INC_DLFCG9_TBS_2336 | J13: Brillio | K13: DLF Cyber Greens - Tower D & E, 9th Floor | L13: Operations | M13: Food & Beverages | N13: 46078.354 | O13: No | P13: Coffee machine milk container is overflowing with water Requester: Vishwajeet Kumar | Q13: The vendor has fixed the sensor and the container is working properly now. - Close | R13: Closed | S13: Sree Prabhu | T13: 46078.401 | U13: Sree Prabhu | V13: 46078.401
A14: Noida | B14: Capital City BPTP | C14: 24-Feb-26 | D14: Feb'26 | E14: 15 | F14: 10 - 20 Days | G14: 0 | H14: 2335 | I14: INC_BPTPCC14_TBS_2335 | J14: ZS Associates | K14: BPTP Capital City, 14th Floor | L14: Engineering & Building Services | M14: Electrical | N14: 46077.951 | O14: No | P14: Battery terminal lugs were found damaged. Where : 14th Floor UPS Room How : The issue was identified during a routine inspection of the battery bank. Root Cause Analysis (RCA) is awaited from the OEM vendor. Requester: Vishwajeet Kumar Singh | Q14: The faulty battery terminal lugs have been replaced by the OEM team. All battery terminals have been thoroughly cleaned to remove carbon deposits and corrosion. Proper torque tightening has been carried out strictly as per OEM-recommended standards. Anti-corrosion petroleum jelly / terminal protective grease has been applied to all terminals to prevent future oxidation and corrosion. During future PPM (Planned Preventive Maintenance) visits, we will ensure that: Proper torque tightening is carried out as per OEM specifications. Tightening is done in our presence to avoid any gaps or loose connections. A detailed checklist verification is completed before closure of the activity. We will continue to closely monitor the battery bank condition to prevent recurrence of such issues. have been replaced by the OEM team. All battery terminals have been cleaned properly. Proper torque tightening has been carried out as per OEM standards. Anti-corrosion petroleum jelly / terminal protective grease has been applied.also we have ensured that the OEM team Jab PPM karegi toh usko sahi tarkie se tighneing karayenge aur apne samne karayenge taki koi gap Na ho - Close | R14: Closed | S14: Sree Prabhu | T14: 46078.399 | U14: Sree Prabhu | V14: 46078.399
A15: Noida | B15: Capital City BPTP | C15: 24-Feb-26 | D15: Feb'26 | E15: 15 | F15: 10 - 20 Days | G15: 0 | H15: 2327 | I15: INC_BPTPCC_TBS_2327 | J15: ZS Associates | K15: BPTP Capital City | L15: Engineering & Building Services | M15: Safety security systems | N15: 46077.396 | O15: No | P15: What: False fire alarm activated. How: The smoke detector was triggered due to excessive smoke generated when an associate accidentally over-grilled bread in the pantry area. REQUESTER - Vishwajeet | Q15: The team immediately inspected the fire alarm panel to identify the exact location of activation. The smoke detector was checked and cleaned, and the Fire Alarm System (FAS) panel was reset on the same time,also announcement has been done as TS standard speech.A briefing was conducted with the concerned associate and ZS security personnel to avoid recurrence. also A safety advisory will be circulated to all employees regarding proper use of grilling/toasting equipment and the importance of not leaving appliances unattended. - Close | R15: Closed | S15: Ravi | T15: 46077.43 | U15: Ravi | V15: 46077.43
... A32: Gurugram | B32: DLF 10 B&C | C32: 03-Feb-26 | D32: Feb'26 | E32: 36 | F32: 30 + Days | G32: 0 | H32: 2205 | I32: INC_DLFCC10B14_TBS_2205 | J32: Tresvista | K32: DLF Cyber City 10B&C, 14th Floor | L32: Engineering & Building Services | M32: Others (Engineering) | N32: 46056.715 | O32: Yes | P32: What: PU material leaked from RCC. How: Upon inspection, we have checked the PU is leaking from Terrace. REQUESTER - Abhishek Singh | Q32: we have checked the leakage thoroughly and with the help of DLF team, cleared PU from carpet and Cabin Glass. - Close | R32: Closed | S32: Ravi | T32: 46057.399 | U32: Ravi | V32: 46057.399
A33: Gurugram | B33: DLF 10 B&C | C33: 03-Feb-26 | D33: Feb'26 | E33: 36 | F33: 30 + Days | G33: 1 | H33: 2202 | I33: INC_DLFBCC10_TBS_2202 | J33: Centrient Pharma | K33: DLF Cyber City - Building No. 10 - Tower B & C, 10th Floor | L33: Operations | M33: Pest Control | N33: 46056.646 | O33: No | P33: What: Pest issue was raised by the client. REQUESTER - Gautami Choithwani | R33: Open | S33: Ravi | T33: 46056.706 | U33: Ravi | V33: 46056.706
A34: Gurugram | B34: DLF 10 B&C | C34: 03-Feb-26 | D34: Feb'26 | E34: 36 | F34: 30 + Days | G34: 1 | H34: 2201 | I34: INC_DLFCC10BC_TBS_2201 | J34: Circle K | K34: DLF Cyber City 10B&C | L34: Operations | M34: Pest Control | N34: 46056.618 | O34: No | P34: What: Pest issue was raised by the client in pantry and cafeteria areas. REQUESTER - Gautami Choithwani | R34: Open | S34: Ravi | T34: 46056.694 | U34: Ravi | V34: 46056.694
A35: Gurugram | B35: DLF 10 B&C | C35: 02-Feb-26 | D35: Feb'26 | E35: 37 | F35: 30 + Days | G35: 0 | H35: 2189 | I35: INC_DLF10BF9_TBS_2189 | J35: Circle K | K35: DLF Cyber City 10B&C, 9th floor | L35: Engineering & Building Services | M35: Electrical | N35: 46055 | O35: No | P35: What: ACS is not working. How: Upon inspection, we have checked the SMPS is not working. REQUESTER - Abhishek Singh | Q35: we have checked the SMPS supply and found input voltage is ok but not provided the output voltage. We are aligned the vendor to change the SMPS. - Close | R35: Closed | S35: Ravi | T35: 46055.74 | U35: Ravi | V35: 46055.74
A36: Gurugram | B36: Good Earth Business Bay II | C36: 28-Jan-26 | D36: Jan'26 | E36: 42 | F36: 30 + Days | G36: 0 | H36: 2167 | I36: INC_GOBB23_TBS_2167 | J36: Table Space | K36: Good Earth Business Bay II, 3rd Floor | L36: Engineering & Building Services | M36: Plumbing | N36: 46050.826 | O36: No | P36: What: Geyser outlet pipe is damaged. How: Not specified. REQUESTER - Sonu Kumar Giri | Q36: The in-house team has checked the issue and found the geyser outlet pipe to be damaged. Initially the inhouse team closed the valve to prevent the water leakage and also aligned the project team for replacement of the geyser pipe. - Close | R36: Closed | S36: Ravi | T36: 46051.526 | U36: Ravi | V36: 46051.526
A37: Gurugram | B37: Cyber Green | C37: 29-Jan-26 | D37: Jan'26 | E37: 41 | F37: 30 + Days | G37: 0 | H37: 2163 | I37: INC_DLFCG6_TBS_2163 | J37: PricewaterhouseCoopers Service Delivery Center (Kolkata) Private Limited | K37: DLF Cyber Greens - Tower D & E, 6th Floor | L37: Operations | M37: Food & Beverages | N37: 46051.333 | O37: No | P37: What: Coffee machine and Water dispenser are not working. How: Power supply issue for the machine and dispenser. REQUESTER - Yastika Sikka | Q37: On-site MST has temporarily resolved the same. The wiring will be changed by vendor this weekend. - Close | R37: Closed | S37: Ravi | T37: 46051.406 | U37: Ravi | V37: 46051.406
A38: Gurugram | B38: Two Horizon | C38: 28-Jan-26 | D38: Jan'26 | E38: 42 | F38: 30 + Days | G38: 0 | H38: 2160 | I38: INC_TH10_TBS_2160 | J38: Alphagrep Securities | K38: Two Horizon 10th Floor | L38: Engineering & Building Services | M38: Plumbing | N38: 46050.438 | O38: No | P38: What: Sprinkler line leakage from the SS flexible joint Where: Near pantry area How: Not specified Requester: Sonu | Q38: The in-house team has checked the water leakage and the building team has been notified to rectify the issue. - Close | R38: Closed | S38: Sree Prabhu | T38: 46050.656 | U38: Sree Prabhu | V38: 46050.656
A39: Noida | B39: DLF Tech Park | C39: 27-Jan-26 | D39: Jan'26 | E39: 43 | F39: 30 + Days | G39: 0 | H39: 2151 | I39: INC_DLFTP6_TBS_2151 | J39: Table Space | K39: DLF Tech Park, 6th Floor | L39: Engineering & Building Services | M39: Carpentry | N39: 46049.625 | O39: No | P39: What: chair suddenly broken while employee was seated on chair Requester: Pankaj Kumar | Q39: Defective chair quarantined and replaced; [X] similar chairs inspected with [Y] removed; fasteners retorqued; and asked vendor to replace all the similar types of chairs - Close | R39: Closed | S39: Sree Prabhu | T39: 46049.779 | U39: Sree Prabhu | V39: 46049.779
A40: Gurugram | B40: DLF 6 | C40: 26-Jan-26 | D40: Jan'26 | E40: 44 | F40: 30 + Days | G40: 0 | H40: 2148 | I40: INC_DLFCB64_TBS_2148 | J40: ETS India | K40: DLF Cyber City, Building 6, 4th Floor | L40: Engineering & Building Services | M40: Electrical | N40: 46048.819 | O40: No | P40: What: UPS display is faulty. REQUESTER - Sonu Kumar Giri | Q40: The in-house team has checked the UPS display, and the UPS vendor has been aligned for repair/resolution. - Close | R40: Closed | S40: Ravi | T40: 46049.412 | U40: Ravi | V40: 46049.412
A41: Noida | B41: Capital City BPTP | C41: 26-Jan-26 | D41: Jan'26 | E41: 44 | F41: 30 + Days | G41: 0 | H41: 2147 | I41: INC_BPTPCC10_TBS_2147 | J41: Clearwater Analytics | K41: BPTP Capital City, 10th Floor | L41: Security | M41: Unauthorized Access | N41: 46048.521 | O41: No | P41: What: Police officers visit on operational floor at Republic Day. There was an unannounced visit by police officers in the mentioned premise at BPTP Capital city over a complaint raised through 112 - Police Helpline by Clearwater team stating that the office was operational on a public holiday. The police officers were allowed into the operational floor without any prior intimidation to the Tablespace Administration team . The police officers have further connected with the admin team of Clearwater Analytics and will investigate further in correspondence with the occurred incident. REQUESTER - Auroshikha Das | Q41: Tenants will be reminded to ensure that all statutory compliance documents, including wage slips, statutory approvals, and holiday declarations, are readily available during public holiday operations. Clearwater Analytics shared employee wage slips and other compliance-related documents with the police. Initial verification confirmed that wage payments and holiday-related compliances were in order. Police officers coordinated directly with the Clearwater administrative team for further review and investigation. - Close | R41: Closed | S41: Ravi | T41: 46049.409 | U41: Ravi | V41: 46049.409
A42: Noida | B42: DLF Tech Park | C42: 25-Jan-26 | D42: Jan'26 | E42: 45 | F42: 30 + Days | G42: 0 | H42: 2145 | I42: INC_DLFTP5_TBS_2145 | J42: Topsoe India Private Limited | K42: DLF Tech Park, 5th Floor | L42: Engineering & Building Services | M42: Electrical | N42: 46047.458 | O42: No | P42: What: RCCB found melted. How: During the yearly planned shutdown activity, the in-house team inspected the electrical system and identified that the RCCB feeding the Topsoe server rack had melted. REQUESTER - Anoop Singh | Q42: 1-The damaged RCCB was immediately replaced with a new RCCB of the same rating. 2-All terminal connections of the new RCCB were properly tightened as per manufacturer torque specifications. 3-A detailed inspection of the associated server rack power connections was carried out to ensure no further abnormalities. 4-Periodic preventive maintenance checks, including torque verification of critical electrical connections, have been added to the maintenance schedule to prevent recurrence. - Close | R42: Closed | S42: Ravi | T42: 46049.397 | U42: Ravi | V42: 46049.397
A43: Gurugram | B43: Cyber Green | C43: 24-Jan-26 | D43: Jan'26 | E43: 46 | F43: 30 + Days | G43: 0 | H43: 2141 | I43: INC_DLFCG7_TBS_2141 | J43: Table Space | K43: DLF Cyber Greens - Tower D & E, 7th Floor | L43: Engineering & Building Services | M43: Safety security systems | N43: 46046.521 | O43: No | P43: False alarm activated. What: smoke detector activated. REQUESTER - Yastika Sikka | Q43: In-house MST checked the smoke detector, which was activated due to dust, now working normal. - Close | R43: Closed | S43: Ravi | T43: 46046.566 | U43: Ravi | V43: 46046.566
A44: Gurugram | B44: DLF 10 B&C | C44: 23-Jan-26 | D44: Jan'26 | E44: 47 | F44: 30 + Days | G44: 0 | H44: 2137 | I44: INC_DLFCC10B14_TBS_2137 | J44: Tresvista | K44: DLF Cyber City 10B&C, 14th Floor | L44: Engineering & Building Services | M44: Civil | N44: 46045.868 | O44: No | P44: Water leakage from the ceiling *Where*:Workstation area *How*: There was the leakage from the terrace Requester: Sonu | Q44: The in-house team had checked the ceiling and water is coming from the terrace we have informed the Building team to rectify the water leakage issue - Close | R44: Closed | S44: Sree Prabhu | T44: 46046.397 | U44: Sree Prabhu | V44: 46046.397
A45: Noida | B45: Capital City BPTP | C45: 22-Jan-26 | D45: Jan'26 | E45: 48 | F45: 30 + Days | G45: 0 | H45: 2129 | I45: INC_BPTPCC15_TBS_2129 | J45: Nimbuspay Innovations India Private Limited | K45: BPTP Capital City, 15th Floor | L45: Health & Safety | M45: Medical Emergencies | N45: 46044.444 | O45: No | P45: What: The incident occurred near the car parking lift. How: The associate was standing near the car parking lift and checking his wallet. During that time, the lift button was pressed. The valet service staff assumed that no associate was standing near the lift, which led to the incident and caused a minor scratch injury. The associate sustained a minor scratch on the toes REQUESTER - Vishwajeet Kumar Singh | Q45: We have highlighted the issue to the builder and clearly said Instruct valet service staff to ensure clear visual confirmation of the lift area before pressing the lift button. Conduct a safety briefing/training for all valet and support staff on safe lift operation and awareness of surrounding personnel. Install clear safety signage near the car parking lift area indicating “Check Area Before Operating Lift.” Assign defined standing zones near the lift to prevent associates from standing too close during operation. - Close | R45: Closed | S45: Ravi | T45: 46044.508 | U45: Ravi | V45: 46044.508
A46: Gurugram | B46: Good Earth Business Bay II | C46: 20-Jan-26 | D46: Jan'26 | E46: 50 | F46: 30 + Days | G46: 0 | H46: 2124 | I46: INC_GOBB23_TBS_2124 | J46: BAYSTREET ADVISORS PRIVATE LIMITED | K46: Good Earth Business Bay II, 3rd Floor | L46: Engineering & Building Services | M46: Electrical | N46: 46042.75 | O46: No | P46: What: Internet connectivity outage. How: Under investigation. REQUESTER - Shweta sharma | Q46: Aakash Pandey - Close | R46: Closed | S46: Ravi | T46: 46043.728 | U46: Ravi | V46: 46043.728
... A87: Gurugram | B87: DLF 10 B&C | C87: 05-Dec-25 | D87: Dec'25 | E87: 96 | F87: 30 + Days | G87: 0 | H87: 1921 | I87: INC_DLFBCC10_TBS_1921 | J87: Baker Hughes | K87: DLF Cyber City - Building No. 10 - Tower B & C, 10th Floor | L87: Engineering & Building Services | M87: Plumbing | N87: 45996.312 | O87: Yes | P87: Water dripping/seepage observed through the ceiling in both Ladies’ and Gents’ washrooms. How: Water leakage was identified coming from the ceiling in both washrooms. The leak appears to be originating from construction/renovation activities taking place on the 11th floor above the affected location. requester: Jetin Negi | Q87: DLF team corrected the damage - Close | R87: Closed | S87: Sree Prabhu | T87: 45996.469 | U87: Sree Prabhu | V87: 45996.469
A88: Gurugram | B88: DLF 10 B&C | C88: 04-Dec-25 | D88: Dec'25 | E88: 97 | F88: 30 + Days | G88: 1 | H88: 1918 | I88: INC_DLFBCC3_TBS_1918 | J88: Table Space | K88: DLF Cyber City 10B&C, 3rd Floor | L88: Engineering & Building Services | M88: Electrical | N88: 45995.764 | O88: No | P88: Printer provided to the client faced an interruption in service Where: 3rd Floor How: The invoices need to be raised for the vendor Requester: Gautami Choithwani | R88: Open | S88: Sree Prabhu | T88: 45996.455 | U88: Sree Prabhu | V88: 45996.455
A89: Gurugram | B89: DLF 10 B&C | C89: 04-Dec-25 | D89: Dec'25 | E89: 97 | F89: 30 + Days | G89: 0 | H89: 1916 | I89: INC_DLFBCC10_TBS_1916 | J89: SSandC | K89: DLF Cyber City - Building No. 10 - Tower B & C, 10th Floor | L89: Engineering & Building Services | M89: Safety security systems | N89: 45995.625 | O89: No | P89: What*: Smoke detector activated *Where*: 10th Floor *How*: Due to dust *Impact*: No impact | Q89: The team checked the smoke detector and found that it was activated due to dust. The detector has been cleaned, and the panel is now working properly. - Close | R89: Closed | S89: Nivedita MC | T89: 45995.889 | U89: Nivedita MC | V89: 45995.889
A90: Gurugram | B90: DLF 10 B&C | C90: 04-Dec-25 | D90: Dec'25 | E90: 97 | F90: 30 + Days | G90: 0 | H90: 1913 | I90: INC_DLFCC10BC_TBS_1913 | J90: Table Space | K90: DLF Cyber City 10B&C | L90: Engineering & Building Services | M90: Plumbing | N90: 45995.5 | O90: No | P90: What: Watet leakage observed in the handicap washroom from the ceiling How: Due to ongoing construction work in the upper floor | Q90: The builder has been contacted to provide resolution. - Close | R90: Closed | S90: Nivedita MC | T90: 45995.881 | U90: Nivedita MC | V90: 45995.881
A91: Gurugram | B91: DLF 10 B&C | C91: 04-Dec-25 | D91: Dec'25 | E91: 97 | F91: 30 + Days | G91: 0 | H91: 1910 | I91: INC_DLFCC10BC_TBS_1910 | J91: Table Space | K91: DLF Cyber City 10B&C | L91: Engineering & Building Services | M91: Plumbing | N91: 45995.479 | O91: No | P91: *What* : Urinals in the gent's washroom are blocked *How* : There is a blockage in the urinal due to blockage in the drain line. | Q91: Blockage was removed manually from the second floor WC line. Fire pressure treatment was also done. HK staff has been properly briefed and trained to prevent such cases from happening and a prevantative process has been communicated. - Close | R91: Closed | S91: Nivedita MC | T91: 45995.874 | U91: Nivedita MC | V91: 45995.874
A92: Noida | B92: Capital City BPTP | C92: 04-Dec-25 | D92: Dec'25 | E92: 97 | F92: 30 + Days | G92: 0 | H92: 1909 | I92: INC_BPTPCC9_TBS_1909 | J92: Naviga | K92: BPTP Capital City, 9th Floor | L92: Others | M92: Others | N92: 45995.583 | O92: No | P92: What: Misuse of the Naviga photocopy machine by a Table Space security staff member. How: The individual was not aware that the photocopy machine belonged to the client (Naviga) | Q92: The concerned security guard was counseled and warned regarding the misuse of client property. The security team was briefed about strict adherence to authorization protocols. A short awareness session was conducted for all ground staff, clearly instructing them not to use any client-owned machines, tools, or materials without formal approval. The incident was logged for internal compliance monitoring. - Close | R92: Closed | S92: Nivedita MC | T92: 45995.872 | U92: Nivedita MC | V92: 45995.872
A93: Gurugram | B93: Cyber Green | C93: 03-Dec-25 | D93: Dec'25 | E93: 98 | F93: 30 + Days | G93: 0 | H93: 1908 | I93: INC_DLFCG10_TBS_1908 | J93: Alight Solutions | K93: DLF Cyber Greens - Tower D & E, 10th Floor | L93: Operations | M93: Pest Control | N93: 45994.562 | O93: No | P93: Cockroach spotted on workstation, how: Under investigation: REQUESTER - Yastika Sikka | Q93: Pest control and sanitization has been done - Close | R93: Closed | S93: Ravi | T93: 45995.407 | U93: Ravi | V93: 45995.407
A94: Gurugram | B94: DLF 10 B&C | C94: 02-Dec-25 | D94: Dec'25 | E94: 99 | F94: 30 + Days | G94: 0 | H94: 1900 | I94: INC_DLFBCC3_TBS_1900 | J94: Table Space | K94: DLF Cyber City 10B&C, 3rd Floor | L94: Engineering & Building Services | M94: Electrical | N94: 45993.417 | O94: Yes | P94: Emergency UPS output supply was tripped Requester: Sonu Kumar Giri | Q94: OEM had checked the UPS and found that it was a short circuit on the output breaker. The team had identified with the OEM and resolved the issue, but the system has been kept under observation for 24 hours. - Close | R94: Closed | S94: Sree Prabhu | T94: 45993.617 | U94: Sree Prabhu | V94: 45993.617
A95: Gurugram | B95: DLF 10 B&C | C95: 02-Dec-25 | D95: Dec'25 | E95: 99 | F95: 30 + Days | G95: 0 | H95: 1899 | I95: INC_DLF10BF9_TBS_1899 | J95: Circle K | K95: DLF Cyber City 10B&C, 9th floor | L95: Engineering & Building Services | M95: Electrical | N95: 45993.444 | O95: No | P95: The dishwasher in the pantry is not working How : Certain parts are faulty Requester: Yuktha Manthpal | Q95: The faulty parts were replaced - Close | R95: Closed | S95: Sree Prabhu | T95: 45993.615 | U95: Sree Prabhu | V95: 45993.615
A96: Noida | B96: Capital City BPTP | C96: 27-Nov-25 | D96: Nov'25 | E96: 104 | F96: 30 + Days | G96: 0 | H96: 1883 | I96: INC_BPTPCC9_TBS_1883 | J96: Naviga | K96: BPTP Capital City, 9th Floor | L96: Engineering & Building Services | M96: Electrical | N96: 45988 | O96: No | P96: PFC card failure in Module No. 4 of the 100kVA KEOR MOD UPS How : Root Cause Analysis (RCA) is awaited from the OEM vendor partner (Numeric) Requester: Vishwajeet | Q96: The faulty Module No. 4 has been replaced with a new module. The issue has been escalated to the OEM (Numeric) for detailed testing and confirmation of root cause. Internal management has already been informed regarding the failure and replacement.Request OEM Numeric to conduct a detailed root cause analysis (RCA) of the failed PFC card. Perform regular thermal checks, dust cleaning, and preventive maintenance of PFC boards. Ensure stable input power supply and check for any incoming surge issues. Keep spare modules/cards available for immediate replacement in future. - Close | R96: Closed | S96: Sree Prabhu | T96: 45989.403 | U96: Sree Prabhu | V96: 45989.403
A97: Gurugram | B97: DLF Downtown - Gurgaon | C97: 26-Nov-25 | D97: Nov'25 | E97: 105 | F97: 30 + Days | G97: 0 | H97: 1878 | I97: INC_DT16_TBS_1878 | J97: Mishcon De Reya | K97: DLF Downtown - Block 4, Gurugram, 16th Floor | L97: Operations | M97: Animal Movement | N97: 45987.674 | O97: No | P97: A bat entered from the shaft area. How: The MST team was checking the shaft area, and the bat entered from there. Requester: Priyanka Malhotra | Q97: With the help of the housekeeping team, the operations team guided the bat outside safely. - Close | R97: Closed | S97: Sree Prabhu | T97: 45987.889 | U97: Sree Prabhu | V97: 45987.889
A98: Gurugram | B98: DLF 10 B&C | C98: 26-Nov-25 | D98: Nov'25 | E98: 105 | F98: 30 + Days | G98: 0 | H98: 1875 | I98: INC_DLFCC10BC_TBS_1875 | J98: Table Space | K98: DLF Cyber City 10B&C | L98: Engineering & Building Services | M98: Plumbing | N98: 45987.514 | O98: No | P98: Water was found overflowing from the WC in the handicapped washroom. The overflow caused water to spread across the floor, creating a slip hazard. Where: Handicapped Washroom Cause (How): Pipeline blockage Requester Jetin Negi | Q98: Vendor conduced the drainoscopy to rectify the issue. - Close | R98: Closed | S98: Sree Prabhu | T98: 45987.882 | U98: Sree Prabhu | V98: 45987.882
A99: Gurugram | B99: Two Horizon | C99: 25-Nov-25 | D99: Nov'25 | E99: 106 | F99: 30 + Days | G99: 0 | H99: 1870 | I99: INC_TH10_TBS_1870 | J99: Table Space | K99: Two Horizon 10th Floor | L99: Security | M99: Theft or Loss | N99: 45986.576 | O99: No | P99: One of the three PlayStation 5 controllers is missing. How: Investigation awaited from Security Requester: Amit Thakur | Q99: The process has been updated to client and system updated - Close | R99: Closed | S99: Sree Prabhu | T99: 45986.819 | U99: Sree Prabhu | V99: 46000.803
A100: Gurugram | B100: DLF 10 B&C | C100: 24-Nov-25 | D100: Nov'25 | E100: 107 | F100: 30 + Days | G100: 0 | H100: 1856 | I100: INC_DLF10B5_TBS_1856 | J100: SSandC | K100: DLF Cyber City 10B&C, 5th floor | L100: Engineering & Building Services | M100: Plumbing | N100: 45985.479 | O100: Yes | P100: WC main drain line blockage How: The WC drain line became blocked Requester: Sonu Kumar Giri | Q100: The team has checked the WC drain line and cleared it. The blockage issue has now been resolved. - Close | R100: Closed | S100: Sree Prabhu | T100: 45985.735 | U100: Sree Prabhu | V100: 45985.735
... A183: Gurugram | B183: DLF Downtown - Gurgaon | C183: 02-Aug-25 | D183: Aug'25 | E183: 221 | F183: 30 + Days | G183: 0 | H183: 1273 | I183: INC_DT16_TBS_1273 | J183: Table Space | K183: DLF Downtown - Block 4, Gurugram, 16th Floor | L183: Security | M183: Unauthorized Access | N183: 45871.681 | O183: No | P183: One of the staff of Sulaksham vendor whose name was Jasram was using the TS employee ID card to access the Table Space floor. The security supervisor observed and Informed to Reginal security lead. The access card was confiscated as per the direction of Security lead. | Q183: ID card confiscated. Informed to the TS employee whose ID was found. - Close | R183: Closed | S183: Sree Prabhu | T183: 45871.885 | U183: Sree Prabhu | V183: 45871.885
A184: Noida | B184: Capital City BPTP | C184: 30-Jul-25 | D184: Jul'25 | E184: 224 | F184: 30 + Days | G184: 0 | H184: 1262 | I184: INC_BPTPCC_TBS_1262 | J184: Table Space | K184: BPTP Capital City | L184: Engineering & Building Services | N184: 45868.75 | O184: No | P184: The water supply suddenly stopped | Q184: Immediate coordination was carried out with the builder/facility team to refill the overhead water tank installed on the terrace, resulting in restoration of the water supply. we have advised to regularly monitor tank levels and ensure the existing automated water level monitoring system (if available) is functional. Additionally, the preventive maintenance schedule is to be reviewed and strictly implemented to prevent recurrence of such issues - Close | R184: Closed | S184: Facility Coordinator BPTP | T184: 45868.776 | U184: Facility Coordinator BPTP | V184: 45868.776
A185: Gurugram | B185: DLF 8 | C185: 30-Jul-25 | D185: Jul'25 | E185: 224 | F185: 30 + Days | G185: 0 | H185: 1260 | I185: INC_DLFCC8B_TBS_1260 | J185: Table Space | K185: DLF Cyber City - Building No. 8 - Tower B, 7th Floor | L185: Health & Safety | M185: Medical Emergencies | N185: 45868.542 | O185: No | P185: Female security personnel fainted at the reception area. How: The incident occurred due to suspected lack of oxygen, causing the staff member to lose consciousness. | Q185: Proper medical check completed - Close | R185: Closed | S185: Ravi | T185: 45868.612 | U185: Ravi | V185: 45868.612
A186: Gurugram | B186: DLF 6 | C186: 27-Jul-25 | D186: Jul'25 | E186: 227 | F186: 30 + Days | G186: 0 | H186: 1247 | I186: INC_DLFCB64_TBS_1247 | J186: ETS India | K186: DLF Cyber City, Building 6, 4th Floor | L186: Engineering & Building Services | M186: Electrical | N186: 45865.083 | O186: Yes | P186: MCB tripped, power supply cut from the workstations due to a faulty system wire. | Q186: Faulty wire has been removed and MCB has been switched on and kept under observation - Close | R186: Closed | S186: Puneet Gautam | T186: 45868.451 | U186: Puneet Gautam | V186: 45868.451
A187: Gurugram | B187: Cyber Green | C187: 29-Jul-25 | D187: Jul'25 | E187: 225 | F187: 30 + Days | G187: 0 | H187: 1246 | I187: INC_DLFCG10_TBS_1246 | J187: Alight Solutions | K187: DLF Cyber Greens - Tower D & E, 10th Floor | L187: Engineering & Building Services | M187: Civil | N187: 45867.889 | O187: No | P187: water dripping from the 10th floor ceiling. | Q187: Issue has been resolved by the vendor partner and they have briefed about being mindful about the work done - Close | R187: Closed | S187: Sree Prabhu | T187: 45868.412 | U187: Sree Prabhu | V187: 45868.412
A188: Noida | B188: Capital City BPTP | C188: 29-Jul-25 | D188: Jul'25 | E188: 225 | F188: 30 + Days | G188: 0 | H188: 1245 | I188: INC_BPTPCC9_TBS_1245 | J188: Table Space | K188: BPTP Capital City, 9th Floor | L188: Security | M188: Access control/CCTV/Security System | N188: 45867 | O188: No | P188: Access control of 6 pax and 12 pax meeting room are non-functional. | Q188: The issue was immediately highlighted to the in-house team, and a new power socket was installed for the access controller. Following the installation, the access control system resumed normal functionality. Going forward, we will ensure that all necessary power and connectivity provisions are considered during any new system installations to avoid such incidents. - Close | R188: Closed | S188: Dushyant Singh | T188: 45867.662 | U188: Dushyant Singh | V188: 45867.662
A189: Gurugram | B189: DLF 10 B&C | C189: 28-Jul-25 | D189: Jul'25 | E189: 226 | F189: 30 + Days | G189: 0 | H189: 1241 | I189: INC_DLFCC10B14_TBS_1241 | J189: Tresvista | K189: DLF Cyber City 10B&C, 14th Floor | L189: Engineering & Building Services | M189: Carpentry | N189: 45866.736 | O189: No | P189: Ceiling tile of lady's washroom has fallen off due to pigeon and rat entry | Q189: The team has identified the location where the gap was present. The builder has since refilled the gap to prevent such issues from occurring in the future. - Close | R189: Closed | S189: Yukta Mathpal | T189: 45867.533 | U189: Yukta Mathpal | V189: 45867.672
A190: Noida | B190: Capital City BPTP | C190: 28-Jul-25 | D190: Jul'25 | E190: 226 | F190: 30 + Days | G190: 0 | H190: 1238 | I190: INC_BPTPCC_TBS_1238 | J190: Thermofisher | K190: BPTP Capital City | L190: Traffic & Transport | M190: Vehicle Damage | N190: 45866.417 | O190: No | P190: Client- Thermofisher Vehicle Damage in the parking when the building team park the vehicle. | Q190: The responsible parties have been identified. Repairs have been scheduled/completed for the affected vehicles. The building team has been briefed on revised parking protocols and reminded of their responsibilities to prevent future occurrences. Additional signage and access controls have been recommended/implemented to minimize risk. - Close | R190: Closed | S190: Facility Coordinator BPTP | T190: 45866.703 | U190: Facility Coordinator BPTP | V190: 45866.703
A191: Noida | B191: Capital City BPTP | C191: 25-Jul-25 | D191: Jul'25 | E191: 229 | F191: 30 + Days | G191: 0 | H191: 1236 | I191: INC_BPTPCC15_TBS_1236 | J191: Atkins | K191: BPTP Capital City, 15th Floor | L191: Health & Safety | N191: 45863.771 | O191: No | P191: Mr. Divya Kumar Pandey, one of employees, slipped in the washroom due to a wet and slippery floor | Q191: Same has been Security personnel promptly responded and administered first aid to the injured employee at the location, also ensure regular and documented housekeeping checks in all common areas, especially washrooms, at frequent intervals, also we have conduct training and awareness for housekeeping staff on immediate response to spills and the importance of safety signage,Maintain cleaning logs with time-stamped entries and staff signatures to track routine inspections. - Close | R191: Closed | S191: FE Tech BPTPCC | T191: 45866.567 | U191: FE Tech BPTPCC | V191: 45866.567
A192: Gurugram | B192: DLF 10 B&C | C192: 28-Jul-25 | D192: Jul'25 | E192: 226 | F192: 30 + Days | G192: 0 | H192: 1234 | I192: INC_DLFBCC3_TBS_1234 | J192: Table Space | K192: DLF Cyber City 10B&C, 3rd Floor | L192: Health & Safety | M192: Medical Emergencies | N192: 45866.396 | O192: No | P192: A housekeeping staff member slipped and tripped on the cafe floor sue to oil spillage. | Q192: The team is intructed to work more carefully going forward - Close | R192: Closed | S192: Yukta Mathpal | T192: 45866.433 | U192: Yukta Mathpal | V192: 45866.433
A193: Noida | B193: Capital City BPTP | C193: 28-Jul-25 | D193: Jul'25 | E193: 226 | F193: 30 + Days | G193: 0 | H193: 1232 | I193: INC_BPTPCC9_TBS_1232 | J193: Table Space | K193: BPTP Capital City, 9th Floor | L193: Engineering & Building Services | N193: 45866.375 | O193: No | P193: Temperature is not maintained as per standard due to air blockage in the chiller line | Q193: Same has been informed to the builder team, internal management as well. Builder team is working on it for resolving the issue, At the same time, the builder team did air punching in the terrace area due to which air came out of the line and the temperature got maintained as per statndard - Close | R193: Closed | S193: FE Tech BPTPCC | T193: 45866.384 | U193: FE Tech BPTPCC | V193: 45866.384
A194: Noida | B194: Capital City BPTP | C194: 27-Jul-25 | D194: Jul'25 | E194: 227 | F194: 30 + Days | G194: 0 | H194: 1230 | I194: INC_BPTPCC9_TBS_1230 | J194: Naviga | K194: BPTP Capital City, 9th Floor | L194: Engineering & Building Services | N194: 45865 | O194: No | P194: 100kVA ups module fan failure | Q194: Same has been replaced faulty fan by the OEM team also Maintenance schedule reviewed to ensure periodic cleaning and inspection of fan filters Preventive Maintenance (PM) checklist updated to include more frequent checks for dust accumulation on fans and filters Now ups fan is working fine and all the ups system are working healthyy - Close | R194: Closed | S194: FE Tech BPTPCC | T194: 45865.448 | U194: FE Tech BPTPCC | V194: 45865.448
A195: Gurugram | B195: DLF 10 B&C | C195: 22-Jul-25 | D195: Jul'25 | E195: 232 | F195: 30 + Days | G195: 0 | H195: 1206 | I195: INC_DLF10B5_TBS_1206 | J195: SSandC | K195: DLF Cyber City 10B&C, 5th floor | L195: Engineering & Building Services | M195: Plumbing | N195: 45860.875 | O195: No | P195: Description Of Incident: water dripping issue from the above floor (6th floor) | Q195: Reached the team at the affected area and informed the builder to address and resolve the issue. The builder team has resolved the issue successfully. - Close | R195: Closed | S195: Sree Prabhu | T195: 45861.411 | U195: Sree Prabhu | V195: 45861.411
A196: Noida | B196: Capital City BPTP | C196: 21-Jul-25 | D196: Jul'25 | E196: 233 | F196: 30 + Days | G196: 0 | H196: 1197 | I196: INC_BPTPCC15_TBS_1197 | J196: Table Space | K196: BPTP Capital City, 15th Floor | L196: Engineering & Building Services | M196: Safety security systems | N196: 45859.854 | O196: No | P196: False Alarm activated during sofa cleaning | Q196: The in-house team inspected the area and confirmed that a false alarm was triggered in the C-2 area on the 15th floor, Smoke detector was cleaned at the same time and reset the FAS panel also announcement has been done as per standard speech. And housekeeping team has been strictly briefed to follow proper procedures during cleaning activities to avoid such incidents in the future. - Close | R196: Closed | S196: Facility Coordinator BPTP | T196: 45859.883 | U196: Facility Coordinator BPTP | V196: 45859.883
A197: Gurugram | B197: DLF 6 | C197: 18-Jul-25 | D197: Jul'25 | E197: 236 | F197: 30 + Days | G197: 0 | H197: 1181 | I197: INC_DLFCB64_TBS_1181 | J197: Table Space | K197: DLF Cyber City, Building 6, 4th Floor | L197: Engineering & Building Services | M197: Safety security systems | N197: 45856.681 | O197: No | P197: MCP pushed by the employee accidentally at reception, how: While playing around | Q197: Team had checked for the availibility of MCP key at site & simultaneously, silenced the Fire alarm panel and reset the MCP. Client has been communicated on such scenarios where they to instruct the employees and not get involved in such activities. - Close | R197: Closed | S197: Ravi | T197: 45856.728 | U197: Ravi | V197: 45860.797
A198: Gurugram | B198: DLF 8 | C198: 17-Jul-25 | D198: Jul'25 | E198: 237 | F198: 30 + Days | G198: 0 | H198: 1170 | I198: INC_DLF8B_TBS_1170 | J198: Table Space | K198: DLF Cyber City 8B | L198: Engineering & Building Services | M198: Plumbing | N198: 45855.375 | O198: No | P198: water dripping issue from the top floor, 2 no's ceiling tiles damaged | Q198: Reached the team at the affected area and informed the builder to address and resolve the issue. The builder team has resolved the issue successfully. - Close | R198: Closed | S198: Ravi | T198: 45855.469 | U198: Ravi | V198: 45855.469
A199: Noida | B199: DLF Tech Park | C199: 14-Jul-25 | D199: Jul'25 | E199: 240 | F199: 30 + Days | G199: 0 | H199: 1151 | I199: INC_DLFTP5_TBS_1151 | J199: Topsoe India Private Limited | K199: DLF Tech Park, 5th Floor | L199: Engineering & Building Services | M199: Safety security systems | N199: 45852.736 | O199: No | P199: MCP automatically alarm generated due to faulty reason (Zone B -MCP No-206) | Q199: Inspect and repair or replace faulty MCP units. Check and secure all wiring connections. Ensure MCP enclosures are sealed against moisture. Clean MCP components to remove dust and debris. Stabilize the power supply to the alarm system. Test and service the fire alarm control panel. Implement regular maintenance and monitoring schedules. - Close | R199: Closed | S199: Anoop Singh | T199: 45852.765 | U199: Anoop Singh | V199: 45852.765
A200: Gurugram | B200: Cyber Green | C200: 14-Jul-25 | D200: Jul'25 | E200: 240 | F200: 30 + Days | G200: 0 | H200: 1149 | I200: INC_DLFCG7_TBS_1149 | J200: Table Space | K200: DLF Cyber Greens - Tower D & E, 7th Floor | L200: Health & Safety | M200: Medical Emergencies | N200: 45852.542 | O200: No | P200: one of pwc employee suddenly started having severe stomach pain | Q200: Send Employee to nearest hospital - CloseSuggested to employee don't take the food from outside - Close | R200: Closed | S200: FE CG | T200: 45852.708 | U200: FE CG | V200: 45852.708
A201: Noida | B201: Capital City BPTP | C201: 11-Jul-25 | D201: Jul'25 | E201: 243 | F201: 30 + Days | G201: 0 | H201: 1135 | I201: INC_BPTPCC13_TBS_1135 | J201: Thermofisher | K201: BPTP Capital City, 13th Floor | L201: Engineering & Building Services | M201: Safety security systems | N201: 45849.375 | O201: No | P201: Water Leak ageing from pendant sprinkler line | Q201: This issue was highlighted to the builder team for rectification. Upon inspection, they found that the flexible pipe was loose, which caused water leakage from the sprinkler line. To resolve this, the builder team drained the sprinkler line, properly tightened the flexible pipe with the sprinkler head, and then recharged the sprinkler line. After the corrective work, no leakage was observed during the testing. - Close | R201: Closed | S201: FE Tech BPTPCC | T201: 45849.405 | U201: FE Tech BPTPCC | V201: 45849.405
A202: Gurugram | B202: DLF 10 B&C | C202: 05-Jul-25 | D202: Jul'25 | E202: 249 | F202: 30 + Days | G202: 0 | H202: 1109 | I202: INC_DLFBCC10_TBS_1109 | J202: Baker Hughes | K202: DLF Cyber City - Building No. 10 - Tower B & C, 10th Floor | L202: Engineering & Building Services | M202: Carpentry | N202: 45843.708 | O202: No | P202: The glass appears to have cracked due to spontaneous thermal stress. which caused it to break and fall. | Q202: DLF Team has replaced the broken glass - Close | R202: Closed | S202: Rupesh Srivastav | T202: 45843.755 | U202: Rupesh Srivastav | V202: 45843.755
A203: Gurugram | B203: DLF 10 B&C | C203: 03-Jul-25 | D203: Jul'25 | E203: 251 | F203: 30 + Days | G203: 0 | H203: 1098 | I203: INC_DLFBCC10_TBS_1098 | J203: Table Space | K203: DLF Cyber City - Building No. 10 - Tower B & C, 10th Floor | L203: Health & Safety | M203: Medical Emergencies | N203: 45841.451 | O203: Yes | P203: Security Lady guard Archana had fainted near reception area. | Q203: Lady guard has been advised to take proper rest for recovery. - Close | R203: Closed | S203: Rupesh Srivastav | T203: 45841.463 | U203: Rupesh Srivastav | V203: 45842.521
A204: Noida | B204: Capital City BPTP | C204: 02-Jul-25 | D204: Jul'25 | E204: 252 | F204: 30 + Days | G204: 0 | H204: 1095 | I204: INC_BPTPCC15_TBS_1095 | J204: Atkins | K204: BPTP Capital City, 15th Floor | L204: Engineering & Building Services | N204: 45840.75 | O204: No | P204: Minor water leak ageing from the fire line where on the butterfly valve above the ceiling areas | Q204: The water droplet leakage issue has been escalated to the builder team for necessary rectification. Continuous follow-up is being maintained with the builder to ensure timely resolution. Joint inspection will be conducted with the builder team during the upcoming weekend. Required repair or replacement of the affected valve/pipe section will be carried out based on inspection findings. Final resolution will be confirmed post-rectification, and preventive measures will be taken to avoid recurrence. - Close | R204: Closed | S204: FE Tech BPTPCC | T204: 45840.765 | U204: FE Tech BPTPCC | V204: 45840.765
A205: Noida | B205: Capital City BPTP | C205: 02-Jul-25 | D205: Jul'25 | E205: 252 | F205: 30 + Days | G205: 0 | H205: 1088 | I205: INC_BPTPCC10_TBS_1088 | J205: Clearwater Analytics | K205: BPTP Capital City, 10th Floor | L205: Engineering & Building Services | M205: Electrical | N205: 45840.319 | O205: No | P205: 15kVA UPS No-4 went to bypass mode | Q205: UPS OEM has Team visited the site and identified that the UPS PFC (Power Factor Correction) card is faulty. The replacement PFC card has been received from the OEM team. However, the client has denied permission for a shutdown during working days. We have already initiated communication with the client requesting a shutdown to replace the faulty PFC card. The client has confirmed that the replacement can be carried out on Saturday. Accordingly, the same has been informed to the OEM vendor partner to proceed with the replacement on the scheduled day, the oem team has coming on the site in sat and replaced the faulty PFC card now all systems are working healthy - Close | R205: Closed | S205: FE Tech BPTPCC | T205: 45840.409 | U205: FE Tech BPTPCC | V205: 45840.409
A206: Gurugram | B206: Cyber Green | C206: 29-Jun-25 | D206: Jun'25 | E206: 255 | F206: 30 + Days | G206: 0 | H206: 1076 | I206: INC_DLFCG7_TBS_1076 | J206: Table Space | K206: DLF Cyber Greens - Tower D & E, 7th Floor | L206: Operations | M206: Food & Beverages | N206: 45837.667 | O206: No | P206: What: Microwave plate broken by security personnel How: while reheating the food | Q206: Team member has been briefed to be mindful for future reference and the new plate has been procured through Petty cash - Close | R206: Closed | S206: Sree Prabhu | T206: 45838.558 | U206: Sree Prabhu | V206: 45838.558
A207: Noida | B207: Capital City BPTP | C207: 28-Jun-25 | D207: Jun'25 | E207: 256 | F207: 30 + Days | G207: 0 | H207: 1073 | I207: INC_BPTPCC12_TBS_1073 | J207: Siemens | K207: BPTP Capital City, 12th Floor | L207: Engineering & Building Services | N207: 45836.694 | O207: No | P207: Non VRV split unit not effectively cooling in the Siemens HUB room | Q207: Today vendor has visit at site and conduct nitrogen pressure test and soap bubble test to identify leak points, but there is no any leakages found in the out door and indoor unit, and same has been charge the line with correct type of quantity of refrigerant as per required also we will planned quarterly ppm they have identified the leak inspection test and refrigerant pressure test in quarterly ppm checklist going forward - Close | R207: Closed | S207: FE Tech BPTPCC | T207: 45836.837 | U207: FE Tech BPTPCC | V207: 45836.837
A208: Noida | B208: Capital City BPTP | C208: 26-Jun-25 | D208: Jun'25 | E208: 258 | F208: 30 + Days | G208: 0 | H208: 1068 | I208: INC_BPTPCC_TBS_1068 | J208: Table Space | K208: BPTP Capital City | L208: Health & Safety | M208: Harm to People | N208: 45834.417 | O208: No | P208: "On mentioned 26th June 25 around 10PM, a physical/verbal altercation occurred between [Ashu Kumar- Security guard] and [Pradeep Kumar - HK Supervisor] in the common area of the office premises. According to eyewitness accounts and preliminary observations, the incident began as a verbal disagreement regarding personal comments, The situation escalated when both parties raised their voices and used aggressive language. Despite attempts by nearby colleagues to de-escalate the situation, the confrontation intensified, and physical contact was reportedly made by one or both individuals. Security/intervention was called, and the situation was brought under control within few minutes Both employees were separated and escorted to different areas to prevent further escalation. No severe injuries were reported, but one or both individuals may have sustained minor bruises or emotional distress. An internal investigation has been initiated to gather statements from witnesses and determine the appropriate course of action in accordance with company policy. Both individuals have been temporarily relieved from duty pending the outcome of the investigation. | Q208: Depending on the severity and circumstances of the altercation, disciplinary action range from warning to terminationProvide training on conflict resolution, de-escalation techniques, and workplace violence prevention - Close | R208: Closed | S208: Facility Coordinator BPTP | T208: 45835.756 | U208: Facility Coordinator BPTP | V208: 45838.769
A209: Gurugram | B209: DLF 10 B&C | C209: 23-Jun-25 | D209: Jun'25 | E209: 261 | F209: 30 + Days | G209: 0 | H209: 1042 | I209: INC_DLFBCC10_TBS_1042 | J209: Table Space | K209: DLF Cyber City - Building No. 10 - Tower B & C, 10th Floor | L209: Engineering & Building Services | M209: Plumbing | N209: 45831 | O209: Yes | P209: Wastewater is dripping inside the Handicap washroom from the top floor | Q209: The team reached the location, informed the DLF team, and stopped the water supply to the floor. - Close | R209: Closed | S209: FE Tech GG | T209: 45832.594 | U209: FE Tech GG | V209: 45832.594
A210: Gurugram | B210: DLF 10 B&C | C210: 23-Jun-25 | D210: Jun'25 | E210: 261 | F210: 30 + Days | G210: 0 | H210: 1041 | I210: INC_DLFBCC10_TBS_1041 | J210: NTT India Private Limited | K210: DLF Cyber City - Building No. 10 - Tower B & C, 10th Floor | L210: Engineering & Building Services | M210: Plumbing | N210: 45831 | O210: No | P210: Water dripping from the CSU unit | Q210: Cleaned the drain line by the building team - Close | R210: Closed | S210: FE Tech GG | T210: 45832.59 | U210: FE Tech GG | V210: 45832.59
A211: Noida | B211: Capital City BPTP | C211: 24-Jun-25 | D211: Jun'25 | E211: 260 | F211: 30 + Days | G211: 0 | H211: 1040 | I211: INC_BPTPCC14_TBS_1040 | J211: ZS Associates | K211: BPTP Capital City, 14th Floor | L211: Engineering & Building Services | N211: 45832.542 | O211: No | P211: MCP pulled mistakenly by HK by during cleaning | Q211: MCP and FAS panel has reset by the MST inhouse team and the system is now functioning normally, All House keeping staff were briefed and re-trained on emergency equipment protocol,announcement has been done as standard TS guide line. - Close | R211: Closed | S211: FE Tech BPTPCC | T211: 45832.581 | U211: FE Tech BPTPCC | V211: 45832.581
A212: Gurugram | B212: Cyber Green | C212: 21-Jun-25 | D212: Jun'25 | E212: 263 | F212: 30 + Days | G212: 0 | H212: 1038 | I212: INC_DLFCG9_TBS_1038 | J212: Table Space | K212: DLF Cyber Greens - Tower D & E, 9th Floor | L212: Security | M212: Theft or Loss | N212: 45829.569 | O212: Yes | P212: Mr. Sanjay Kumar Facility executive TS, took the store key from the reception. He took out the material from the store at 9 floor cyber greens and gave it to Abdul kuddus -Pantry boy and Sukdev Minz - House boy and sent the material to building No- 5 without informing security. The material was sent out from Cyber greens to Building no 5 where guard Harshit detected material in their pockets. There was no approval of Regional lead nor gate pass were made for material transfer. | Q212: Refer the attached investigation report - Close | R212: Closed | S212: Dushyant Singh | T212: 45831.77 | U212: Dushyant Singh | V212: 45832.579
A213: Gurugram | B213: DLF 8 | C213: 19-Jun-25 | D213: Jun'25 | E213: 265 | F213: 30 + Days | G213: 0 | H213: 1031 | I213: INC_DLF8B_TBS_1031 | J213: Mycom | K213: DLF Cyber City 8B | L213: Health & Safety | N213: 45827 | O213: Yes | P213: Fire Alaram not activated during the fire drill | Q213: 1-MST missed pulling the MCP during mockdrill, hence warning letter issued to him and training provided - Close2-Fire alarm system has been integrated with Access control system and programming and testing has been done - Close3- Facility team conducted meeting and shared the information about description of assembly area and TS placard - Close | R213: Closed | S213: FE Tech GG | T213: 45828.435 | U213: FE Tech GG | V213: 45829.768
A214: Gurugram | B214: DLF 10 B&C | C214: 17-Jun-25 | D214: Jun'25 | E214: 267 | F214: 30 + Days | G214: 1 | H214: 1019 | I214: INC_DLFCC10B14_TBS_1019 | J214: Tresvista | K214: DLF Cyber City 10B&C, 14th Floor | L214: Others | M214: Natural Disasters | N214: 45825 | O214: Yes | P214: Rainwater leakage issue from the terrace | R214: Open | S214: FE Tech GG | T214: 45825.766 | U214: FE Tech GG | V214: 45825.766
A215: Noida | B215: Capital City BPTP | C215: 13-Jun-25 | D215: Jun'25 | E215: 271 | F215: 30 + Days | G215: 0 | H215: 1004 | I215: INC_BPTPCC9_TBS_1004 | J215: Table Space | K215: BPTP Capital City, 9th Floor | L215: Engineering & Building Services | M215: Electrical | N215: 45821.361 | O215: No | P215: 100 kVA ups module fan failure alarm showing on the display | Q215: Same has been replaced faulty fan by the OEM team also Maintenance schedule reviewed to ensure periodic cleaning and inspection of fan filters Preventive Maintenance (PM) checklist updated to include more frequent checks for dust accumulation on fans and filters Now ups fan is working fine and all the ups system are working healthyy - Close | R215: Closed | S215: FE Tech BPTPCC | T215: 45821.416 | U215: FE Tech BPTPCC | V215: 45821.416
A216: Gurugram | B216: Two Horizon | C216: 10-Jun-25 | D216: Jun'25 | E216: 274 | F216: 30 + Days | G216: 0 | H216: 988 | I216: INC_TH10_TBS_988 | J216: Truecaller | K216: Two Horizon 10th Floor | L216: Engineering & Building Services | M216: HVAC | N216: 45818.396 | O216: No | P216: CSU getting tripped and not maintaining standard temperature | Q216: Belts have been replaced and air pockets has been released - Close | R216: Closed | S216: Akshay Singh | T216: 45818.49 | U216: Akshay Singh | V216: 45818.728
A217: Gurugram | B217: Two Horizon | C217: 07-Jun-25 | D217: Jun'25 | E217: 277 | F217: 30 + Days | G217: 0 | H217: 984 | I217: INC_TH9_TBS_984 | J217: Table Space | K217: Two Horizon Centre, 9th Floor | L217: Engineering & Building Services | M217: Plumbing | N217: 45815.521 | O217: Yes | P217: water logging found under the raised floor of UPS room and workstation area | Q217: Opening gaps has been sealed with cement - Close | R217: Closed | S217: Akshay Singh | T217: 45817.719 | U217: Akshay Singh | V217: 45817.726
A218: Noida | B218: Capital City BPTP | C218: 30-May-25 | D218: May'25 | E218: 285 | F218: 30 + Days | G218: 0 | H218: 952 | I218: INC_BPTPCC13_TBS_952 | J218: Thermofisher | K218: BPTP Capital City, 13th Floor | L218: Engineering & Building Services | M218: Plumbing | N218: 45807 | O218: No | P218: Water leak ageing from the ceiling in the handicapped washroom | Q218: Same has been aligned to the builder team to check the leak ageing issue and share root cause for us, builder team checked and found there is leak aging from the PVC pipe line which was going to the flushing tank. same time the leaking joint in the PVC line was repaired with proper sealing material. Water flow was restored and tested to ensure no further leakage. - Close | R218: Closed | S218: FE Tech BPTPCC | T218: 45807.953 | U218: FE Tech BPTPCC | V218: 45807.953
A219: Noida | B219: Capital City BPTP | C219: 28-May-25 | D219: May'25 | E219: 287 | F219: 30 + Days | G219: 0 | H219: 944 | I219: INC_BPTPCC13_TBS_944 | J219: Table Space | K219: BPTP Capital City, 13th Floor | L219: Others | N219: 45805 | O219: Yes | P219: False Aram Activate | Q219: In House team has checked the location and found false alarm has activated on the particular location, same has been informed to the client and internal management as well after that silence the FAS panel and cleaned the detector and reset the FAS panel panel. also announcement has been done as per TS standard speech - Close | R219: Closed | S219: Facility Coordinator BPTP | T219: 45805.824 | U219: Facility Coordinator BPTP | V219: 45805.824
A220: Noida | B220: Capital City BPTP | C220: 22-May-25 | D220: May'25 | E220: 293 | F220: 30 + Days | G220: 0 | H220: 911 | I220: INC_BPTPCC9_TBS_911 | J220: Naviga | K220: BPTP Capital City, 9th Floor | L220: Engineering & Building Services | N220: 45799.771 | O220: No | P220: Some water logging found under the raise flooring, | Q220: Builder team and inhouse team with work together and Re-fix and seal the PVC line properly and Inspect all shaft pipe installations before closing the area also Train workers on proper pipe fitting techniques & now it closed properly - Close | R220: Closed | S220: Facility Coordinator BPTP | T220: 45799.885 | U220: Facility Coordinator BPTP | V220: 45799.885
A221: Gurugram | B221: Cyber Green | C221: 19-May-25 | D221: May'25 | E221: 296 | F221: 30 + Days | G221: 0 | H221: 892 | I221: INC_DLFCG_TBS_892 | J221: Alight Solutions | K221: DLF Cyber Greens - Tower D & E | L221: Engineering & Building Services | M221: HVAC | N221: 45796 | O221: No | P221: HVAC services not working with standards temperature | Q221: AHU is under monitoring - Close | R221: Closed | S221: Akshay Singh | T221: 45797.519 | U221: Akshay Singh | V221: 45797.519
A222: Noida | B222: Capital City BPTP | C222: 19-May-25 | D222: May'25 | E222: 296 | F222: 30 + Days | G222: 0 | H222: 888 | I222: INC_BPTPCC10_TBS_888 | J222: Clearwater Analytics | K222: BPTP Capital City, 10th Floor | L222: Others | M222: Others | N222: 45796.604 | O222: No | P222: Currency exchange vendor of clearwater has claimed that he forgot his currency envelop on the Clear water reception area from where it got misplaced now he is complaining that somebody stolen his envelop with currency and file a case against a pantry associate Mr. Ishu. at nearest police station where Cops has visited to our building premises to get the statement recorded. | Q222: TS team has extended the support where inquiry was conducted police in station where support has been extended - Close | R222: Closed | S222: FE Tech BPTPCC | T222: 45796.684 | U222: FE Tech BPTPCC | V222: 45796.684
A223: Gurugram | B223: DLF 10 B&C | C223: 16-May-25 | D223: May'25 | E223: 299 | F223: 30 + Days | G223: 0 | H223: 876 | I223: INC_DLFBCC10_TBS_876 | J223: Table Space | K223: DLF Cyber City - Building No. 10 - Tower B & C, 10th Floor | L223: Engineering & Building Services | M223: Electrical | N223: 45793 | O223: No | P223: No Power back-up for the emergency lights. | Q223: We have successfully connected the emergency lighting system to an alternate power source and coordinated with the vendor partner for an on-site visit. During the inspection process, two batteries were found to be faulty. These batteries have now been replaced. The UPS is currently operational and functioning as expected - Close | R223: Closed | S223: FE Tech GG | T223: 45793.762 | U223: FE Tech GG | V223: 45797.722
A224: Noida | B224: Capital City BPTP | C224: 13-May-25 | D224: May'25 | E224: 302 | F224: 30 + Days | G224: 0 | H224: 857 | I224: INC_BPTPCC_TBS_857 | J224: Table Space | K224: BPTP Capital City | L224: Engineering & Building Services | M224: HVAC | N224: 45790.25 | O224: No | P224: Leak aging issue in the chiller line | Q224: Builder team has aligned the OEM team to rectfy the issue where issue chiller line has been repaired and cooling has been resume as per given timeline - Close | R224: Closed | S224: FE Tech BPTPCC | T224: 45790.302 | U224: FE Tech BPTPCC | V224: 45790.302
A225: Noida | B225: Capital City BPTP | C225: 08-May-25 | D225: May'25 | E225: 307 | F225: 30 + Days | G225: 0 | H225: 842 | I225: INC_BPTPCC13_TBS_842 | J225: Trintech | K225: BPTP Capital City, 13th Floor | L225: Engineering & Building Services | M225: Others (Engineering) | N225: 45785 | O225: No | P225: Car Damage Due to Parking Infrastructure | Q225: Builder has agreed to reimburse amount under insurance act - Close | R225: Closed | S225: Lipin Dua | T225: 45785.5 | U225: Lipin Dua | V225: 45785.5
A226: Gurugram | B226: Cyber Green | C226: 07-May-25 | D226: May'25 | E226: 308 | F226: 30 + Days | G226: 0 | H226: 839 | I226: INC_DLFCG9_TBS_839 | J226: Brillio | K226: DLF Cyber Greens - Tower D & E, 9th Floor | L226: Others | M226: Others | N226: 45784 | O226: Yes | P226: Mr. Alok was stopped the DLF team to park his vehicle as we have allocated different slots to Brillio team as per their request. | Q226: We connected with the builder team and brief them on the slot allocation to Brillio team - Close | R226: Closed | S226: Mohd Kamran | T226: 45784.442 | U226: Mohd Kamran | V226: 45784.442
A227: Noida | B227: Capital City BPTP | C227: 06-May-25 | D227: May'25 | E227: 309 | F227: 30 + Days | G227: 0 | H227: 837 | I227: INC_BPTPCC9_TBS_837 | J227: Table Space | K227: BPTP Capital City, 9th Floor | L227: Others | M227: Others | N227: 45783.667 | O227: No | P227: unauthorized disclosure of confidential pictures of House maid 1 by another house maid 2 while changing her clothes in washroom. | Q227: Inform to UDS team for further action. warning letter has been issued along with deletion of all snaps taken on phone.and briefing has been done - Close | R227: Closed | S227: Facility Coordinator BPTP | T227: 45783.749 | U227: Facility Coordinator BPTP | V227: 45783.749
A228: Gurugram | B228: DLF 8 | C228: 05-May-25 | D228: May'25 | E228: 310 | F228: 30 + Days | G228: 0 | H228: 835 | I228: INC_DLFCC8B_TBS_835 | J228: IAC | K228: DLF Cyber City - Building No. 8 - Tower B, 7th Floor | L228: Engineering & Building Services | M228: Others (Engineering) | N228: 45782 | O228: No | P228: Urinal glass Partition has been broken | Q228: Cleaned the Glass particle & informed with the Vendor to install new partition - Close | R228: Closed | S228: FE Tech GG | T228: 45783.536 | U228: FE Tech GG | V228: 45783.536
A229: Gurugram | B229: Two Horizon | C229: 02-May-25 | D229: May'25 | E229: 313 | F229: 30 + Days | G229: 0 | H229: 830 | I229: INC_THC_TBS_830 | J229: ELAN LLP | K229: Two Horizon Center | L229: Engineering & Building Services | M229: Civil | N229: 45779 | O229: Yes | P229: Due to heavy rainfall, some leakages observed from facade glass in the office area. | Q229: Slicon sealant applied - Close | R229: Closed | S229: Akshay Singh | T229: 45782.484 | U229: Akshay Singh | V229: 45782.484
A230: Gurugram | B230: Cyber Green | C230: 28-Apr-25 | D230: Apr'25 | E230: 317 | F230: 30 + Days | G230: 0 | H230: 829 | I230: INC_DLFCG10_TBS_829 | J230: Alight Solutions | K230: DLF Cyber Greens - Tower D & E, 10th Floor | L230: Engineering & Building Services | M230: HVAC | N230: 45775 | O230: Yes | P230: The HVAC System was not effective and took a long time to maintain the ambient temp due to malfunction in one of the parts of the AHU | Q230: Informed the Builder team to check the issue and rectify and in the meantime bypass the AHU to a different chiller plant and created a group with the builder team to moniter the temp on hourly basis - Close | R230: Closed | S230: Mohd Kamran | T230: 45782.473 | U230: Mohd Kamran | V230: 45782.473
A231: Noida | B231: Capital City BPTP | C231: 04-May-25 | D231: May'25 | E231: 311 | F231: 30 + Days | G231: 0 | H231: 825 | I231: INC_BPTPCC15_TBS_825 | J231: CBRE D&T | K231: BPTP Capital City, 15th Floor | L231: Others | N231: 45781 | O231: No | P231: Meeting Room Glass break | Q231: Area has been barricade along with putting up warning signages. client spoc has been informed on replacement of toughened glass within 3-4 business day . toughened glass has been replaced - Close | R231: Closed | S231: Facility Coordinator BPTP | T231: 45781.714 | U231: Facility Coordinator BPTP | V231: 45781.714
A232: Noida | B232: DLF Tech Park | C232: 30-Apr-25 | D232: Apr'25 | E232: 315 | F232: 30 + Days | G232: 0 | H232: 821 | I232: INC_DLFTP5_TBS_821 | J232: Topsoe India Private Limited | K232: DLF Tech Park, 5th Floor | L232: Others | M232: Others | N232: 45777.375 | O232: No | P232: A smoke detector got activated due to dishwasher machine steam while pantry staff washing Mugs. | Q232: Brief given to team - Close | R232: Closed | S232: Pankaj Kumar | T232: 45778.404 | U232: Pankaj Kumar | V232: 45778.404
A233: Gurugram | B233: DLF 8 | C233: 25-Apr-25 | D233: Apr'25 | E233: 320 | F233: 30 + Days | G233: 0 | H233: 806 | I233: INC_DLF8B_TBS_806 | J233: Table Space | K233: DLF Cyber City 8B | L233: Engineering & Building Services | M233: Electrical | N233: 45772 | O233: No | P233: Showing the Error in the 75 KVA UPS | Q233: Informed to OEM team to further rectification - Close | R233: Closed | S233: FE Tech GG | T233: 45775.553 | U233: FE Tech GG | V233: 45775.553
A234: Gurugram | B234: Cyber Green | C234: 25-Apr-25 | D234: Apr'25 | E234: 320 | F234: 30 + Days | G234: 0 | H234: 804 | I234: INC_DLFCG7_TBS_804 | J234: PricewaterhouseCoopers Service Delivery Center (Kolkata) Private Limited | K234: DLF Cyber Greens - Tower D & E, 7th Floor | L234: Engineering & Building Services | M234: Plumbing | N234: 45772 | O234: No | P234: Water Logging issue inside the AHU room | Q234: Team reached at the place & Informed with the builder team - Close | R234: Closed | S234: FE Tech GG | T234: 45775.481 | U234: FE Tech GG | V234: 45775.481
A235: Gurugram | B235: DLF 10 B&C | C235: 25-Apr-25 | D235: Apr'25 | E235: 320 | F235: 30 + Days | G235: 0 | H235: 799 | I235: INC_DLFBCC10_TBS_799 | J235: Table Space | K235: DLF Cyber City - Building No. 10 - Tower B & C, 10th Floor | L235: Engineering & Building Services | M235: Safety security systems | N235: 45772 | O235: No | P235: Fire Alarm Triggered | Q235: PA Announcement has been made to avoid any panic situation - Close | R235: Closed | S235: Rupesh Srivastav | T235: 45772.719 | U235: Rupesh Srivastav | V235: 45772.719
A236: Noida | B236: Capital City BPTP | C236: 24-Apr-25 | D236: Apr'25 | E236: 321 | F236: 30 + Days | G236: 0 | H236: 791 | I236: INC_BPTPCC10_TBS_791 | J236: Clearwater Analytics | K236: BPTP Capital City, 10th Floor | L236: Others | M236: Others | N236: 45771 | O236: No | P236: Rodent Infestation Threatening IT Assets and infra | Q236: Rat Pad has been placed and paste control audit has been carried out to closed the gap if any - Close | R236: Closed | S236: Facility Coordinator BPTP | T236: 45771.762 | U236: Facility Coordinator BPTP | V236: 45771.762
A237: Noida | B237: DLF Tech Park | C237: 23-Apr-25 | D237: Apr'25 | E237: 322 | F237: 30 + Days | G237: 0 | H237: 784 | I237: INC_DLFTP5_TBS_784 | J237: Topsoe India Private Limited | K237: DLF Tech Park, 5th Floor | L237: Others | M237: Others | N237: 45770.333 | O237: No | P237: Due to water logging at 6th floor and we don't know from where the water is travelling and reaching the 5th floor. Specially on and near reception area. | Q237: Brief to project team to take care - Close | R237: Closed | S237: Pankaj Kumar | T237: 45770.397 | U237: Pankaj Kumar | V237: 45770.397
A238: Noida | B238: DLF Tech Park | C238: 18-Apr-25 | D238: Apr'25 | E238: 327 | F238: 30 + Days | G238: 0 | H238: 770 | I238: INC_DLFTP5_TBS_770 | J238: Topsoe India Private Limited | K238: DLF Tech Park, 5th Floor | L238: Others | M238: Others | N238: 45765 | O238: Yes | P238: False fire alarm activated due to cleaning of vacuum filter, | Q238: Breief team to take care - Close | R238: Closed | S238: Facility Coordinator BPTP | T238: 45765.693 | U238: Facility Coordinator BPTP | V238: 45769.372
...
